Workbook

Sheet Start here
A1: Financing capability map — capabilities, key KPIs and opportunities
A2: Prepared by Arpit Shah · October 2026. Public sources read on 7 October 2026. Blue cells are inputs; black cells are formulas.
A4: What this is
A5: A map of what a markets financing platform has to do: 49 capabilities in 10 domains, from the products on the desk to the technology estate. Each domain carries the KPI it is judged on. Each capability is rated on how much three technology changes will alter it: AI; distributed ledgers and tokenization; and new liquidity instruments and market structure. The opportunities tab places stability and innovation work by when it could start.
A6: KPI values are internal to each institution and are left to be baselined. Ratings are first judgments and opportunities are hypotheses, to be corrected by the people who own the books, the queues and the platforms.
A8: How to read this workbook
A9: Tab | B9: What it holds
A10: 2 · Domains | B10: The 10 domains: what each covers, its exposure to the three technology changes, its key KPI with a public reference point, two further KPIs to watch, and cells for the current value and target.
A11: 3 · Capabilities | B11: The 49 capabilities: what each is, why it matters, what each technology change alters, a rating of 0 to 3 on each, and the opportunities and KPIs linked to it.
A12: 4 · Opportunities | B12: 25 opportunities by type and horizon, with why now, the KPIs each moves, a first proof point and a status.
A14: Rating scale (Capabilities tab, columns I–K)
A15: Rating | B15: Means | E15: Capabilities rated so on AI | F15: on DLT | G15: on instruments
A16: 0 | B16: None | E16: =COUNTIF(Capabilities!$I$5:$I$53,A16) -> 0 | F16: =COUNTIF(Capabilities!$J$5:$J$53,A16) -> 1 | G16: =COUNTIF(Capabilities!$K$5:$K$53,A16) -> 2
A17: 1 | B17: Peripheral | E17: =COUNTIF(Capabilities!$I$5:$I$53,A17) -> 25 | F17: =COUNTIF(Capabilities!$J$5:$J$53,A17) -> 19 | G17: =COUNTIF(Capabilities!$K$5:$K$53,A17) -> 12
A18: 2 | B18: Material within 24 months | E18: =COUNTIF(Capabilities!$I$5:$I$53,A18) -> 11 | F18: =COUNTIF(Capabilities!$J$5:$J$53,A18) -> 16 | G18: =COUNTIF(Capabilities!$K$5:$K$53,A18) -> 19
A19: 3 | B19: Reshapes the capability | E19: =COUNTIF(Capabilities!$I$5:$I$53,A19) -> 13 | F19: =COUNTIF(Capabilities!$J$5:$J$53,A19) -> 13 | G19: =COUNTIF(Capabilities!$K$5:$K$53,A19) -> 16
A21: At a glance
A22: Domains | B22: =ROWS(Domains!$B$5:$B$14) -> 10
A23: Capabilities | B23: =ROWS(Capabilities!$B$5:$B$53) -> 49
A24: Capabilities with a total of 7 or more (of 9) | B24: =COUNTIF(Capabilities!$L$5:$L$53,">=7") -> 11
A25: Average total rating (0–9) | B25: =AVERAGE(Capabilities!$L$5:$L$53) -> 5.5918367
A26: Key KPIs baselined (current and target set) | B26: =ROWS(Domains!$R$5:$R$14)-COUNTIF(Domains!$R$5:$R$14,"Not set") -> 0
A27: Key KPIs on target | B27: =COUNTIF(Domains!$R$5:$R$14,"On target") -> 0
A29: Opportunities by type and horizon (tab 4)
A30: Type | B30: Now | C30: Next | D30: Later | E30: Total | F30: Confirmed | G30: In flight
A31: Stability | B31: =COUNTIFS(Opportunities!$B$5:$B$29,$A31,Opportunities!$G$5:$G$29,"Now") -> 7 | C31: =COUNTIFS(Opportunities!$B$5:$B$29,$A31,Opportunities!$G$5:$G$29,"Next") -> 5 | D31: =COUNTIFS(Opportunities!$B$5:$B$29,$A31,Opportunities!$G$5:$G$29,"Later") -> 0 | E31: =SUM(B31:D31) -> 12 | F31: =COUNTIFS(Opportunities!$B$5:$B$29,$A31,Opportunities!$K$5:$K$29,"Confirmed") -> 0 | G31: =COUNTIFS(Opportunities!$B$5:$B$29,$A31,Opportunities!$K$5:$K$29,"In flight") -> 0
A32: Innovation | B32: =COUNTIFS(Opportunities!$B$5:$B$29,$A32,Opportunities!$G$5:$G$29,"Now") -> 4 | C32: =COUNTIFS(Opportunities!$B$5:$B$29,$A32,Opportunities!$G$5:$G$29,"Next") -> 6 | D32: =COUNTIFS(Opportunities!$B$5:$B$29,$A32,Opportunities!$G$5:$G$29,"Later") -> 3 | E32: =SUM(B32:D32) -> 13 | F32: =COUNTIFS(Opportunities!$B$5:$B$29,$A32,Opportunities!$K$5:$K$29,"Confirmed") -> 0 | G32: =COUNTIFS(Opportunities!$B$5:$B$29,$A32,Opportunities!$K$5:$K$29,"In flight") -> 0
A33: All opportunities | B33: =SUM(B31:B32) -> 11 | C33: =SUM(C31:C32) -> 11 | D33: =SUM(D31:D32) -> 3 | E33: =SUM(E31:E32) -> 25 | F33: =SUM(F31:F32) -> 0 | G33: =SUM(G31:G32) -> 0
A35: Horizon: Now = first six months · Next = six to eighteen months · Later = beyond eighteen months.

Sheet Domains
A1: Domains — the ten domains, each with the KPI it is judged on
A2: One row per domain: what it covers, how exposed its capabilities are to the three technology changes (formulas over the Capabilities tab), and its key KPI with a public reference point. KPI values are internal to each institution and are not shown: Current and Target are inputs (blue), and Status then computes.
A4: # | B4: Domain | C4: What it covers | D4: Capabilities | E4: AI (avg) | F4: DLT (avg) | G4: Instruments (avg) | H4: Total (avg, 0–9) | I4: Change led by | J4: Key KPI | K4: Good is | L4: Reviewed | M4: What the KPI measures | N4: Public reference point | O4: Also watched | P4: Current | Q4: Target | R4: Status
A5: 1 | B5: Financing products & desks | C5: What the desk trades and lends: repo, securities lending, prime and spread-product financing. | D5: =COUNTIF(Capabilities!$B$5:$B$53,B5) -> 6 | E5: =AVERAGEIF(Capabilities!$B$5:$B$53,B5,Capabilities!$I$5:$I$53) -> 1.3333333 | F5: =AVERAGEIF(Capabilities!$B$5:$B$53,B5,Capabilities!$J$5:$J$53) -> 1.6666667 | G5: =AVERAGEIF(Capabilities!$B$5:$B$53,B5,Capabilities!$K$5:$K$53) -> 2.3333333 | H5: =AVERAGEIF(Capabilities!$B$5:$B$53,B5,Capabilities!$L$5:$L$53) -> 5.3333333 | I5: =IF(E5=MAX(E5:G5),"AI",IF(F5=MAX(E5:G5),"Ledgers and tokenization","Instruments and market structure")) -> Instruments and market structure | J5: Financing revenue and growth | K5: Higher | L5: Monthly; quarterly externally | M5: Net revenue from financing across repo, spread-product lending and prime, and its growth on the year. | N5: At one large dealer, financing was $11.4bn of revenue in 2025, 37% of its markets revenue. | O5: Net spread on the book (higher) Client balances (higher) | R5: =IF(OR(P5="",Q5=""),"Not set",IF(K5="Higher",IF(P5>=Q5,"On target",IF(P5>=0.9*Q5,"Watch","Off target")),IF(P5<=Q5,"On target",IF(P5<=1.1*Q5,"Watch","Off target")))) -> Not set
A6: 2 | B6: Trade lifecycle: execution to settlement | C6: From execution to settlement: capture, matching, clearing, settlement and lifecycle events. | D6: =COUNTIF(Capabilities!$B$5:$B$53,B6) -> 5 | E6: =AVERAGEIF(Capabilities!$B$5:$B$53,B6,Capabilities!$I$5:$I$53) -> 1.6 | F6: =AVERAGEIF(Capabilities!$B$5:$B$53,B6,Capabilities!$J$5:$J$53) -> 1.4 | G6: =AVERAGEIF(Capabilities!$B$5:$B$53,B6,Capabilities!$K$5:$K$53) -> 2 | H6: =AVERAGEIF(Capabilities!$B$5:$B$53,B6,Capabilities!$L$5:$L$53) -> 5 | I6: =IF(E6=MAX(E6:G6),"AI",IF(F6=MAX(E6:G6),"Ledgers and tokenization","Instruments and market structure")) -> Instruments and market structure | J6: Straight-through processing | K6: Higher | L6: Daily | M6: Trades booked, confirmed and instructed without manual touch. | N6: 94.8% of US trades were affirmed by 9pm on trade date in April 2026 (DTCC). | O6: Settlement fails and their cost (lower) Cleared share and netting efficiency (higher) | R6: =IF(OR(P6="",Q6=""),"Not set",IF(K6="Higher",IF(P6>=Q6,"On target",IF(P6>=0.9*Q6,"Watch","Off target")),IF(P6<=Q6,"On target",IF(P6<=1.1*Q6,"Watch","Off target")))) -> Not set
A7: 3 | B7: Inventory & position management | C7: Knowing what the firm holds, where it is, and what is free to use. | D7: =COUNTIF(Capabilities!$B$5:$B$53,B7) -> 4 | E7: =AVERAGEIF(Capabilities!$B$5:$B$53,B7,Capabilities!$I$5:$I$53) -> 2.25 | F7: =AVERAGEIF(Capabilities!$B$5:$B$53,B7,Capabilities!$J$5:$J$53) -> 1.75 | G7: =AVERAGEIF(Capabilities!$B$5:$B$53,B7,Capabilities!$K$5:$K$53) -> 1.5 | H7: =AVERAGEIF(Capabilities!$B$5:$B$53,B7,Capabilities!$L$5:$L$53) -> 5.5 | I7: =IF(E7=MAX(E7:G7),"AI",IF(F7=MAX(E7:G7),"Ledgers and tokenization","Instruments and market structure")) -> AI | J7: Inventory put to work | K7: Higher | L7: Daily | M7: How much of the firm's inventory is financed, lent or matched internally. | N7: Survey: about a quarter of collateral earns no return (Nasdaq and ValueExchange, February 2026). | O7: Inventory data freshness (lower) Breaks and reconciliation (lower) | R7: =IF(OR(P7="",Q7=""),"Not set",IF(K7="Higher",IF(P7>=Q7,"On target",IF(P7>=0.9*Q7,"Watch","Off target")),IF(P7<=Q7,"On target",IF(P7<=1.1*Q7,"Watch","Off target")))) -> Not set
A8: 4 | B8: Collateral management & optimization | C8: Deciding what to deliver where, at the lowest cost, within the agreements. | D8: =COUNTIF(Capabilities!$B$5:$B$53,B8) -> 4 | E8: =AVERAGEIF(Capabilities!$B$5:$B$53,B8,Capabilities!$I$5:$I$53) -> 2.25 | F8: =AVERAGEIF(Capabilities!$B$5:$B$53,B8,Capabilities!$J$5:$J$53) -> 2.5 | G8: =AVERAGEIF(Capabilities!$B$5:$B$53,B8,Capabilities!$K$5:$K$53) -> 2.25 | H8: =AVERAGEIF(Capabilities!$B$5:$B$53,B8,Capabilities!$L$5:$L$53) -> 7 | I8: =IF(E8=MAX(E8:G8),"AI",IF(F8=MAX(E8:G8),"Ledgers and tokenization","Instruments and market structure")) -> Ledgers and tokenization | J8: Collateral efficiency | K8: Lower | L8: Daily | M8: Cost of the collateral actually delivered against the cheapest eligible. | N8: Consultant estimates of the saving run from tens to hundreds of millions of dollars a year for large firms; to be tested on the desk's own book. | O8: Margin calls and disputes (lower) Optimizer cadence (higher) | R8: =IF(OR(P8="",Q8=""),"Not set",IF(K8="Higher",IF(P8>=Q8,"On target",IF(P8>=0.9*Q8,"Watch","Off target")),IF(P8<=Q8,"On target",IF(P8<=1.1*Q8,"Watch","Off target")))) -> Not set
A9: 5 | B9: Liquidity, funding & balance sheet | C9: The constraints that decide how much financing can be written. | D9: =COUNTIF(Capabilities!$B$5:$B$53,B9) -> 4 | E9: =AVERAGEIF(Capabilities!$B$5:$B$53,B9,Capabilities!$I$5:$I$53) -> 1.25 | F9: =AVERAGEIF(Capabilities!$B$5:$B$53,B9,Capabilities!$J$5:$J$53) -> 1.25 | G9: =AVERAGEIF(Capabilities!$B$5:$B$53,B9,Capabilities!$K$5:$K$53) -> 2.5 | H9: =AVERAGEIF(Capabilities!$B$5:$B$53,B9,Capabilities!$L$5:$L$53) -> 5 | I9: =IF(E9=MAX(E9:G9),"AI",IF(F9=MAX(E9:G9),"Ledgers and tokenization","Instruments and market structure")) -> Instruments and market structure | J9: Revenue per unit of balance sheet and of risk-weighted assets | K9: Higher | L9: Monthly | M9: How much revenue each dollar of leverage exposure and of RWA produces. | N9: Supplementary leverage ratios at the four largest US dealers ranged from 4.3% to 5.5% at 30 June 2026. | O9: Intraday liquidity usage (lower) Funding cost and term profile (lower) | R9: =IF(OR(P9="",Q9=""),"Not set",IF(K9="Higher",IF(P9>=Q9,"On target",IF(P9>=0.9*Q9,"Watch","Off target")),IF(P9<=Q9,"On target",IF(P9<=1.1*Q9,"Watch","Off target")))) -> Not set
A10: 6 | B10: Risk & control | C10: Counterparty, market and regulatory controls on the financing book. | D10: =COUNTIF(Capabilities!$B$5:$B$53,B10) -> 4 | E10: =AVERAGEIF(Capabilities!$B$5:$B$53,B10,Capabilities!$I$5:$I$53) -> 1.75 | F10: =AVERAGEIF(Capabilities!$B$5:$B$53,B10,Capabilities!$J$5:$J$53) -> 1.25 | G10: =AVERAGEIF(Capabilities!$B$5:$B$53,B10,Capabilities!$K$5:$K$53) -> 1.25 | H10: =AVERAGEIF(Capabilities!$B$5:$B$53,B10,Capabilities!$L$5:$L$53) -> 4.25 | I10: =IF(E10=MAX(E10:G10),"AI",IF(F10=MAX(E10:G10),"Ledgers and tokenization","Instruments and market structure")) -> AI | J10: Control health | K10: Lower | L10: Monthly | M10: Open audit and regulatory issues, and the accuracy of regulatory reporting. | N10: Only 2 of 31 global banks fully met the Basel risk-data principles in the last progress report. | O10: Counterparty exposure and concentration (in range) Regulatory reporting quality (higher) | R10: =IF(OR(P10="",Q10=""),"Not set",IF(K10="Higher",IF(P10>=Q10,"On target",IF(P10>=0.9*Q10,"Watch","Off target")),IF(P10<=Q10,"On target",IF(P10<=1.1*Q10,"Watch","Off target")))) -> Not set
A11: 7 | B11: Technology estate | C11: The platforms themselves: booking, settlement, inventory, optimization, data and resilience. | D11: =COUNTIF(Capabilities!$B$5:$B$53,B11) -> 6 | E11: =AVERAGEIF(Capabilities!$B$5:$B$53,B11,Capabilities!$I$5:$I$53) -> 2 | F11: =AVERAGEIF(Capabilities!$B$5:$B$53,B11,Capabilities!$J$5:$J$53) -> 1.8333333 | G11: =AVERAGEIF(Capabilities!$B$5:$B$53,B11,Capabilities!$K$5:$K$53) -> 2.3333333 | H11: =AVERAGEIF(Capabilities!$B$5:$B$53,B11,Capabilities!$L$5:$L$53) -> 6.1666667 | I11: =IF(E11=MAX(E11:G11),"AI",IF(F11=MAX(E11:G11),"Ledgers and tokenization","Instruments and market structure")) -> Instruments and market structure | J11: Availability of critical services | K11: Higher | L11: Daily; monthly | M11: Uptime of booking, settlement, inventory and optimization during trading and settlement hours. | N11: Market-infrastructure norms: T2S 99.8% in 2025; the Fedwire standard is 99.9%. | O11: Recovery of the position engine (lower) Reference and agreement data readiness (higher) | R11: =IF(OR(P11="",Q11=""),"Not set",IF(K11="Higher",IF(P11>=Q11,"On target",IF(P11>=0.9*Q11,"Watch","Off target")),IF(P11<=Q11,"On target",IF(P11<=1.1*Q11,"Watch","Off target")))) -> Not set
A12: 8 | B12: Engineering leadership & AI engineering | C12: How the platforms are built, changed and modernized, and how AI is applied. | D12: =COUNTIF(Capabilities!$B$5:$B$53,B12) -> 6 | E12: =AVERAGEIF(Capabilities!$B$5:$B$53,B12,Capabilities!$I$5:$I$53) -> 2.8333333 | F12: =AVERAGEIF(Capabilities!$B$5:$B$53,B12,Capabilities!$J$5:$J$53) -> 1.5 | G12: =AVERAGEIF(Capabilities!$B$5:$B$53,B12,Capabilities!$K$5:$K$53) -> 1.1666667 | H12: =AVERAGEIF(Capabilities!$B$5:$B$53,B12,Capabilities!$L$5:$L$53) -> 5.5 | I12: =IF(E12=MAX(E12:G12),"AI",IF(F12=MAX(E12:G12),"Ledgers and tokenization","Instruments and market structure")) -> AI | J12: Deployment frequency and lead time | K12: Higher | L12: Monthly | M12: How often each service ships and how long a change takes. | N12: DORA 2025: 16% of teams deploy on demand; 44% take more than a week from commit to production. | O12: AI-assisted engineering: adoption and effect (higher) Legacy retired and volume on target platforms (higher) | R12: =IF(OR(P12="",Q12=""),"Not set",IF(K12="Higher",IF(P12>=Q12,"On target",IF(P12>=0.9*Q12,"Watch","Off target")),IF(P12<=Q12,"On target",IF(P12<=1.1*Q12,"Watch","Off target")))) -> Not set
A13: 9 | B13: Market structure, competitors & change | C13: The infrastructure, competitors, rules and market conditions around the business. | D13: =COUNTIF(Capabilities!$B$5:$B$53,B13) -> 4 | E13: =AVERAGEIF(Capabilities!$B$5:$B$53,B13,Capabilities!$I$5:$I$53) -> 1 | F13: =AVERAGEIF(Capabilities!$B$5:$B$53,B13,Capabilities!$J$5:$J$53) -> 2.25 | G13: =AVERAGEIF(Capabilities!$B$5:$B$53,B13,Capabilities!$K$5:$K$53) -> 2.5 | H13: =AVERAGEIF(Capabilities!$B$5:$B$53,B13,Capabilities!$L$5:$L$53) -> 5.75 | I13: =IF(E13=MAX(E13:G13),"AI",IF(F13=MAX(E13:G13),"Ledgers and tokenization","Instruments and market structure")) -> Instruments and market structure | J13: Readiness for dated market change | K13: Higher | L13: Monthly | M13: Progress against the clearing mandate, T+1 and longer market hours. | N13: US Treasury clearing: cash by 31 December 2026, repo by 30 June 2027. UK and EU T+1: 11 October 2027. | O13: Share of wallet and rank with priority clients (higher) Technology position against peers (higher) | R13: =IF(OR(P13="",Q13=""),"Not set",IF(K13="Higher",IF(P13>=Q13,"On target",IF(P13>=0.9*Q13,"Watch","Off target")),IF(P13<=Q13,"On target",IF(P13<=1.1*Q13,"Watch","Off target")))) -> Not set
A14: 10 | B14: Digital assets, tokenization & new instruments | C14: Tokenized collateral and cash, intraday liquidity, and how they are treated. | D14: =COUNTIF(Capabilities!$B$5:$B$53,B14) -> 6 | E14: =AVERAGEIF(Capabilities!$B$5:$B$53,B14,Capabilities!$I$5:$I$53) -> 1.1666667 | F14: =AVERAGEIF(Capabilities!$B$5:$B$53,B14,Capabilities!$J$5:$J$53) -> 2.8333333 | G14: =AVERAGEIF(Capabilities!$B$5:$B$53,B14,Capabilities!$K$5:$K$53) -> 2.1666667 | H14: =AVERAGEIF(Capabilities!$B$5:$B$53,B14,Capabilities!$L$5:$L$53) -> 6.1666667 | I14: =IF(E14=MAX(E14:G14),"AI",IF(F14=MAX(E14:G14),"Ledgers and tokenization","Instruments and market structure")) -> Ledgers and tokenization | J14: Connectivity to new venues | K14: Higher | L14: Quarterly | M14: Clearing houses, tokenized venues and tokenized-cash rails connected in production. | N14: About $350bn a day of tokenized repo runs on one platform; three Treasury clearing houses operate from December 2026. | O14: Always-on readiness (higher) Intraday liquidity usage (lower) | R14: =IF(OR(P14="",Q14=""),"Not set",IF(K14="Higher",IF(P14>=Q14,"On target",IF(P14>=0.9*Q14,"Watch","Off target")),IF(P14<=Q14,"On target",IF(P14<=1.1*Q14,"Watch","Off target")))) -> Not set
B15: All domains | D15: =SUM(D5:D14) -> 49 | E15: =AVERAGE(Capabilities!$I$5:$I$53) -> 1.755102 | F15: =AVERAGE(Capabilities!$J$5:$J$53) -> 1.8367347 | G15: =AVERAGE(Capabilities!$K$5:$K$53) -> 2 | H15: =AVERAGE(Capabilities!$L$5:$L$53) -> 5.5918367
A17: How status works: fill Current and Target (blue cells) in the same unit. 'Higher' KPIs are on target at or above the target and on watch within 10% of it; 'Lower' KPIs are the reverse. For 'In range' KPIs enter the usage in Current and its ceiling in Target. Public reference points are context, not targets.

Sheet Capabilities
A1: Capabilities — what a financing platform has to do
A2: 49 capabilities in 10 domains, from the products on the desk to the technology estate. Columns F–H say what each of three technology changes alters; columns I–K are ratings (blue, inputs): 0 none · 1 peripheral · 2 material within 24 months · 3 reshapes the capability. Total and lead are formulas. Ratings are first judgments, to be corrected by the people who own the platforms.
A4: ID | B4: Domain | C4: Capability | D4: What it is | E4: Why it matters | F4: AI — what changes | G4: Ledgers and tokenization — what changes | H4: Instruments and market structure — what changes | I4: AI (0–3) | J4: DLT (0–3) | K4: Instruments (0–3) | L4: Total (0–9) | M4: Change led by | N4: Opportunities | O4: KPIs that depend on it
A5: 1.1 | B5: Financing products & desks | C5: Repo and reverse repo | D5: Financing securities against cash: bilateral and tri-party, cleared and sponsored, GC and specials, open and term, evergreen — and now intraday. | E5: The core financing product; every booking, settlement and inventory decision starts here. | F5: Pricing support for specials; balance-sheet-aware quoting; a read-only desk assistant. | G5: Tokenized repo venues add settlement paths and intraday tenors. | H5: Clearing mandate, sponsored repo and intraday repo change the product itself. | I5: 1 | J5: 2 | K5: 3 | L5: =SUM(I5:K5) -> 6 | M5: =IF(MAX(I5:K5)=0,"—",IF(COUNTIF(I5:K5,MAX(I5:K5))>1,"Mixed",IF(I5=MAX(I5:K5),"AI",IF(J5=MAX(I5:K5),"Ledgers and tokenization","Instruments and market structure")))) -> Instruments and market structure | N5: N7 Intraday repo as a bookable product | O5: Financing revenue and growth Daily P&L and its attribution Net spread on the book Specials and client flow capture
A6: 1.2 | B6: Financing products & desks | C6: Securities lending and borrowing | D6: Lending securities against cash or non-cash collateral; borrowing to cover shorts and fails; agency and principal models. | E6: The second financing product on the platforms; inventory and availability logic depends on it. | F6: Availability, locate and short-interest prediction; fee pricing models. | G6: Tokenized equities and on-ledger pledge are early; the depository's service covers large-cap stocks. | H6: Record lending revenue; loan reporting moved to 2028; 23x5 trading stretches the locate window. | I6: 2 | J6: 1 | K6: 2 | L6: =SUM(I6:K6) -> 5 | M6: =IF(MAX(I6:K6)=0,"—",IF(COUNTIF(I6:K6,MAX(I6:K6))>1,"Mixed",IF(I6=MAX(I6:K6),"AI",IF(J6=MAX(I6:K6),"Ledgers and tokenization","Instruments and market structure")))) -> Mixed | N6: N12 Internalize earlier in the day | O6: Specials and client flow capture
A7: 1.3 | B7: Financing products & desks | C7: Collateral trading, upgrades and transformation | D7: Trading collateral quality: upgrade/downgrade trades, collateral swaps, transformation for margin and HQLA needs. | E7: Where collateral optimization becomes a revenue business rather than a cost function. | F7: What-if and upgrade pricing against the optimizer's cost view. | G7: Collateral swaps settle in minutes on collateral ledgers. | H7: Tokenized funds and digital bonds widen the upgrade universe. | I7: 1 | J7: 3 | K7: 2 | L7: =SUM(I7:K7) -> 6 | M7: =IF(MAX(I7:K7)=0,"—",IF(COUNTIF(I7:K7,MAX(I7:K7))>1,"Mixed",IF(I7=MAX(I7:K7),"AI",IF(J7=MAX(I7:K7),"Ledgers and tokenization","Instruments and market structure")))) -> Ledgers and tokenization | N7: — | O7: —
A8: 1.4 | B8: Financing products & desks | C8: Funding, treasury interface and balance-sheet allocation | D8: How the financing desks fund themselves and are charged: FTP, balance-sheet budgets, matched book vs funding book, quarter-end management. | E8: Explains most of what the desk does that looks irrational from outside; the platforms must expose these costs in real time. | F8: Forecasting balance-sheet usage; allocation recommendations. | G8: Tokenized cash lets funding move outside payment cut-offs. | H8: Funding priced by time of day; leverage and capital rule changes shift capacity. | I8: 1 | J8: 2 | K8: 3 | L8: =SUM(I8:K8) -> 6 | M8: =IF(MAX(I8:K8)=0,"—",IF(COUNTIF(I8:K8,MAX(I8:K8))>1,"Mixed",IF(I8=MAX(I8:K8),"AI",IF(J8=MAX(I8:K8),"Ledgers and tokenization","Instruments and market structure")))) -> Instruments and market structure | N8: N6 Balance sheet and liquidity shown before the trade | O8: Revenue per unit of balance sheet and of risk-weighted assets Balance-sheet and leverage usage against allocation Balance sheet used against budget, intraday Funding cost and term profile
A9: 1.5 | B9: Financing products & desks | C9: Prime finance and synthetic financing | D9: Financing hedge-fund clients: margin lending, securities borrowing, synthetic financing through total return swaps, cross-product margining. The equities-side counterpart of the repo book. | E9: Usually the largest financing balances in a bank sit here. It shares collateral, inventory and balance sheet with fixed-income financing. | F9: Margin and risk models; client reporting assistants. | G9: Client collateral on ledger; requests to post crypto-linked assets. | H9: Record balances; synthetic versus cash mix; cross-product margining; leverage policy. | I9: 1 | J9: 1 | K9: 3 | L9: =SUM(I9:K9) -> 5 | M9: =IF(MAX(I9:K9)=0,"—",IF(COUNTIF(I9:K9,MAX(I9:K9))>1,"Mixed",IF(I9=MAX(I9:K9),"AI",IF(J9=MAX(I9:K9),"Ledgers and tokenization","Instruments and market structure")))) -> Instruments and market structure | N9: N11 One margin and inventory view across prime and fixed-income financing | O9: Financing revenue and growth Client balances Share of wallet and rank with priority clients
A10: 1.6 | B10: Financing products & desks | C10: Spread-product financing and securitization-based lending | D10: Lending against credit assets: warehouse facilities, asset-backed and loan financing, private-credit financing, repo and total-return structures on credit collateral. | E10: A growth focus across large dealers. These are loans on the markets balance sheet with their own collateral, margin and capital logic. | F10: Document extraction for facilities and borrowing-base tests. | G10: Tokenized loans and funds are at an early stage. | H10: Growth in private-credit financing; securitization capital rules. | I10: 2 | J10: 1 | K10: 1 | L10: =SUM(I10:K10) -> 4 | M10: =IF(MAX(I10:K10)=0,"—",IF(COUNTIF(I10:K10,MAX(I10:K10))>1,"Mixed",IF(I10=MAX(I10:K10),"AI",IF(J10=MAX(I10:K10),"Ledgers and tokenization","Instruments and market structure")))) -> AI | N10: — | O10: Financing revenue and growth Client balances Net spread on the book
A11: 2.1 | B11: Trade lifecycle: execution to settlement | C11: Execution and trade capture | D11: Voice and electronic execution (Tradeweb, BrokerTec, MTS, GLMX), booking models, back-to-back and internal trades, novation to CCP. | E11: The front door of the booking platform; booking-model complexity is where legacy accumulates. | F11: Trade capture from chat and voice; anomaly detection on amendments. | G11: Execution on a ledger creates the booking as a by-product. | H11: New venues and tenors add booking models: intraday trades, a choice of clearing house. | I11: 1 | J11: 1 | K11: 2 | L11: =SUM(I11:K11) -> 4 | M11: =IF(MAX(I11:K11)=0,"—",IF(COUNTIF(I11:K11,MAX(I11:K11))>1,"Mixed",IF(I11=MAX(I11:K11),"AI",IF(J11=MAX(I11:K11),"Ledgers and tokenization","Instruments and market structure")))) -> Instruments and market structure | N11: — | O11: Specials and client flow capture Straight-through processing
A12: 2.2 | B12: Trade lifecycle: execution to settlement | C12: Confirmation, matching and reporting | D12: Confirming economics with the counterparty, matching for settlement and for SFTR, generating regulatory reports. | E12: Matching rates and reporting breaks are a visible cost and a regulatory exposure. | F12: Break classification and repair suggestions for reporting fields. | G12: A shared record removes confirmation and matching inside the ledger. | H12: Reporting timetables move; tokenized trades are still reportable. | I12: 2 | J12: 1 | K12: 1 | L12: =SUM(I12:K12) -> 4 | M12: =IF(MAX(I12:K12)=0,"—",IF(COUNTIF(I12:K12,MAX(I12:K12))>1,"Mixed",IF(I12=MAX(I12:K12),"AI",IF(J12=MAX(I12:K12),"Ledgers and tokenization","Instruments and market structure")))) -> AI | N12: — | O12: Straight-through processing Regulatory reporting quality
A13: 2.3 | B13: Trade lifecycle: execution to settlement | C13: Clearing and CCP interaction | D13: Central clearing of repo (FICC GSD, sponsored and agent clearing; LCH RepoClear; Eurex), CCP margin and netting; the US Treasury clearing mandate. | E13: The largest structural change in the book of work: cash by 31 December 2026 and repo by 30 June 2027, with CME and ICE joining FICC as Treasury clearing houses. | F13: Margin forecasting; choosing the clearing house per trade. | G13: Clearing houses begin to accept collateral mobilized on ledgers. | H13: Mandate dates; three Treasury clearing houses; done-away access; cross-margining. | I13: 1 | J13: 1 | K13: 3 | L13: =SUM(I13:K13) -> 5 | M13: =IF(MAX(I13:K13)=0,"—",IF(COUNTIF(I13:K13,MAX(I13:K13))>1,"Mixed",IF(I13=MAX(I13:K13),"AI",IF(J13=MAX(I13:K13),"Ledgers and tokenization","Instruments and market structure")))) -> Instruments and market structure | N13: S8 Design the clearing mandate into the platform | O13: Readiness for dated market change Cleared share and netting efficiency Connectivity to new venues
A14: 2.4 | B14: Trade lifecycle: execution to settlement | C14: Settlement and fails | D14: DVP settlement through Fedwire Securities, DTC, Euroclear, Clearstream and tri-party agents; fails, partials, TMPG fails charges, CSDR penalties. | E14: Where a platform's data quality becomes money: fails charges and penalties are the scoreboard. | F14: Fail prediction, root-cause agents, repair with human release. | G14: Atomic settlement removes fails inside a ledger; boundary fails remain. | H14: T+1 in the UK and EU; 24x5 clearing; penalties. | I14: 3 | J14: 2 | K14: 3 | L14: =SUM(I14:K14) -> 8 | M14: =IF(MAX(I14:K14)=0,"—",IF(COUNTIF(I14:K14,MAX(I14:K14))>1,"Mixed",IF(I14=MAX(I14:K14),"AI",IF(J14=MAX(I14:K14),"Ledgers and tokenization","Instruments and market structure")))) -> Mixed | N14: S4 Consolidate settlement adapters S5 Close the loop on fails S12 Ready for T+1 in the UK and Europe, and for longer hours N3 Predict fails and short covers N4 Operations agents with human release | O14: Cost of failure Settlement fails and their cost Fails caused by data or technology
A15: 2.5 | B15: Trade lifecycle: execution to settlement | C15: Lifecycle events | D15: Rate resets, re-pricing and mark-to-market, substitutions, partial returns, rolls, terminations, corporate actions on collateral. | E15: The event volume that drives platform load and the source of most edge-case defects. | F15: Exception triage on substitutions and re-pricing. | G15: Contracts on ledger automate margin, substitution and coupon events. | H15: Intraday trades multiply event volume. | I15: 1 | J15: 2 | K15: 1 | L15: =SUM(I15:K15) -> 4 | M15: =IF(MAX(I15:K15)=0,"—",IF(COUNTIF(I15:K15,MAX(I15:K15))>1,"Mixed",IF(I15=MAX(I15:K15),"AI",IF(J15=MAX(I15:K15),"Ledgers and tokenization","Instruments and market structure")))) -> Ledgers and tokenization | N15: — | O15: —
A16: 3.1 | B16: Inventory & position management | C16: Positions and inventory | D16: Real-time firm inventory: longs, shorts, box, encumbrance, rehypothecation limits, legal-entity views. | E16: The heart of the estate, and usually its most cache-heavy platform. | F16: Anomaly detection on feeds; inventory questions in plain language. | G16: Ledgers become position sources and locations; a tokenized-entitlement state. | H16: Always-on hours need intraday truth, not snapshots. | I16: 1 | J16: 3 | K16: 2 | L16: =SUM(I16:K16) -> 6 | M16: =IF(MAX(I16:K16)=0,"—",IF(COUNTIF(I16:K16,MAX(I16:K16))>1,"Mixed",IF(I16=MAX(I16:K16),"AI",IF(J16=MAX(I16:K16),"Ledgers and tokenization","Instruments and market structure")))) -> Ledgers and tokenization | N16: S1 Position-engine recovery and peak headroom N1 Intraday collateral optimization N8 Connect to one tokenized repo and collateral venue N11 One margin and inventory view across prime and fixed-income financing | O16: Inventory put to work Inventory data freshness
... A53: 10.6 | B53: Digital assets, tokenization & new instruments | C53: Legal, regulatory and prudential treatment of digital assets | D53: How tokenized securities, tokenized cash and crypto-linked collateral are treated: securities law, custody and client-asset rules, capital and liquidity treatment, master-agreement annexes, new product approval. | E53: Decides what the desk may accept and at what cost. 'Same asset, same treatment' is the working rule in the US, but the detail differs by form: native, mirror or entitlement. | F53: Tracking rule changes across jurisdictions. | G53: The capability itself. | H53: Each instrument needs its own treatment answer. | I53: 1 | J53: 3 | K53: 2 | L53: =SUM(I53:K53) -> 6 | M53: =IF(MAX(I53:K53)=0,"—",IF(COUNTIF(I53:K53,MAX(I53:K53))>1,"Mixed",IF(I53=MAX(I53:K53),"AI",IF(J53=MAX(I53:K53),"Ledgers and tokenization","Instruments and market structure")))) -> Ledgers and tokenization | N53: — | O53: —

Sheet Opportunities
A1: Opportunities — where stability and innovation can move the numbers
A2: 12 stability and 13 innovation opportunities, placed by when they could start. Each names the KPIs it moves and a first proof point. Every row is a hypothesis, built from public material and experience of platforms like these, to be confirmed or dropped with the desk, operations and the engineers; Status is an input (blue). Horizon: Now = first six months · Next = six to eighteen months · Later = beyond eighteen months.
A4: # | B4: Type | C4: Opportunity | D4: What | E4: Why now | F4: Lever | G4: Horizon | H4: Capabilities | I4: KPIs it moves | J4: First proof point | K4: Status
A5: S1 | B5: Stability | C5: Position-engine recovery and peak headroom | D5: Measure and shorten the time to rebuild the in-memory position store after losing a node or a site, and test it at year-end volumes. | E5: In estates built on in-memory grids, recovery and peak volumes are usually where the pain is. To confirm. | F5: Resilience | G5: Now | H5: 7.3 Inventory and position engines 7.6 Architecture, resiliency and performance 3.1 Positions and inventory | I5: Recovery of the position engine Peak performance and headroom Availability of critical services | J5: A recovery test at peak volume, signed off by the engineers. | K5: Hypothesis
A6: S2 | B6: Stability | C6: Service-level objectives and a published baseline | D6: Set objectives and error budgets for booking, settlement, inventory and optimization, and publish delivery and reliability measures monthly. | E6: Clients choose financing providers on reliability; a baseline is the first thing to publish. | F6: Resilience | G6: Now | H6: 7.6 Architecture, resiliency and performance 8.1 Engineering practice and delivery | I6: Availability of critical services Major incidents and time to restore Deployment frequency and lead time Change failure rate | J6: A baseline published in week 3 and every month after. | K6: Hypothesis
A7: S3 | B7: Stability | C7: Remove end-of-day dependencies | D7: Map batch jobs and date rolls, and remove the ones that stop the estate running through the night. | E7: Clearing runs 24x5 already; 23x5 trading starts in December 2026; payment hours lengthen in 2027. | F7: Resilience | G7: Next | H7: 10.4 Intraday and always-on liquidity 7.6 Architecture, resiliency and performance 7.1 Booking and trade-capture platforms | I7: Batch and cut-off performance Always-on readiness | J7: A batch-dependency map with the three that block overnight running. | K7: Hypothesis
A8: S4 | B8: Stability | C8: Consolidate settlement adapters | D8: One internal instruction model with a thin adapter per agent, depository and venue. | E8: Each bespoke adapter is a slow, risky release, and new venues are arriving. | F8: Engineering | G8: Next | H8: 7.2 Settlement and messaging 2.4 Settlement and fails | I8: Straight-through processing Fails caused by data or technology Settlement fails and their cost | J8: An adapter inventory with failure history and the first two to merge. | K8: Hypothesis
A9: S5 | B9: Stability | C9: Close the loop on fails | D9: Feed fail causes and their cost back to booking and to the upkeep of settlement instructions. | E9: Fails usually cluster on a few counterparties and data errors, and the cost is rarely fed back to where the data is kept. To confirm here. | F9: Data | G9: Now | H9: 2.4 Settlement and fails 3.3 Fails and short-cover management 7.5 Data, reference data and integration | I9: Settlement fails and their cost Cost of failure Fails caused by data or technology | J9: A fails Pareto with cost and the three data fixes that remove the most. | K9: Hypothesis
A10: S6 | B10: Stability | C10: Fix repeat breaks at the source | D10: Classify reconciliation breaks by originating feed and event, and fix upstream. | E10: In most estates the same feeds produce the same breaks every day. To confirm here. | F10: Data | G10: Now | H10: 3.4 Books and records reconciliation | I10: Breaks and reconciliation | J10: A break taxonomy by source system. | K10: Hypothesis
A11: S7 | B11: Stability | C11: Control evidence from the pipeline | D11: Tests, approvals and audit evidence captured automatically at release. | E11: Audit findings on technology typically concentrate on change and access evidence; automating it speeds delivery too. | F11: Engineering | G11: Now | H11: 8.1 Engineering practice and delivery 6.3 Regulatory and operational controls | I11: Automated tests and control evidence Open audit and security findings Deployment frequency and lead time | J11: One service releasing with fully automated evidence. | K11: Hypothesis
A12: S8 | B12: Stability | C12: Design the clearing mandate into the platform | D12: Booking, margin and netting that work across several clearing houses, built once. | E12: Cash clearing is due 31 December 2026 and repo 30 June 2027, with two new clearing houses. | F12: Market structure | G12: Now | H12: 2.3 Clearing and CCP interaction 5.2 Balance sheet, capital and netting 7.1 Booking and trade-capture platforms | I12: Readiness for dated market change Cleared share and netting efficiency Connectivity to new venues | J12: An impact map by platform, agreed with the mandate program. | K12: Hypothesis
A13: S9 | B13: Stability | C13: Named owners for reference and agreement data | D13: Golden sources and owners for settlement instructions, agreements and eligibility. | E13: Most fails, disputes and optimizer errors usually trace back to this data. | F13: Data | G13: Now | H13: 7.5 Data, reference data and integration 6.4 Legal agreements and documentation 4.1 Eligibility, haircuts and schedules | I13: Reference and agreement data readiness Fails caused by data or technology | J13: An entity-to-golden-source map with readiness scores. | K13: Hypothesis
A14: S10 | B14: Stability | C14: Relieve the critical people | D14: Move senior engineers off production support through runbooks, automation and cover. | E14: The engineers modernization needs are usually the ones holding production together. To confirm here. | F14: People | G14: Next | H14: 8.4 Team, talent and vendors 7.6 Architecture, resiliency and performance | I14: Team health Run versus change, and cost per trade | J14: A team map with critical-person risk and the first three hires. | K14: Hypothesis
A15: S11 | B15: Stability | C15: Bring the platform up to date | D15: Move runtimes and middleware to supported versions. | E15: Kafka dropped ZooKeeper in 2025, GemFire is subscription-only, and Ignite 2 to 3 is a migration. | F15: Engineering | G15: Next | H15: 7.3 Inventory and position engines 7.6 Architecture, resiliency and performance | I15: Technical debt and platform currency | J15: An end-of-support inventory with dates and owners. | K15: Hypothesis
... A29: N13 | B29: Innovation | C29: Platform interfaces that agents and clients can call | D29: Entitled, audited interfaces for agents and for client systems. | E29: Vendors are exposing agent endpoints; the standards moved to neutral governance in 2025–26. | F29: AI | G29: Later | H29: 8.5 AI in the financing business: decision and execution intelligence 7.5 Data, reference data and integration 9.2 Competitors' offerings and client needs | I29: AI in production on financing data Specials and client flow capture Share of wallet and rank with priority clients | J29: A read-only interface on one service with full audit. | K29: Hypothesis
