Workbook

Sheet README
A1: Citi Services — AI Product Strategy Playbook
A2: Working recommendation for the hiring-manager conversation on AI usage and strategy. Built for the AI Product Strategy, Global Services (Director) mandate. Illustrative figures are labeled; verify anything marked [verify] before sending.
A4: What this workbook is
A5: Item | B5: Content | C5: Notes
A6: Purpose | B6: One place that shows how AI strategy is actually done at a top-tier transaction bank that is mid-pack in enterprise AI adoption — and what Services should do across five mandates: Internal, Client, Pricing, Product, Efficiency.
A7: Diagnosis (one line) | B7: Services is #1 in its markets but Citi is #12 in AI (Evident, Oct 2025, down from #8). The binding constraint is not model capability or spend — it is a governed, repeatable path from pilot to P&L, built on shared data/ontology and pulled by client co-creation.
A8: Guiding policy | B8: Ontology before models · one governed pipeline · reuse over rebuild · co-create with 10 clients before scaling to 10,000 · measure P&L, not pilots.
A9: Coherent actions | B9: 8–10 named bets across the five mandates (see Use-Case Portfolio + Roadmap), a delivery pipeline with tiered controls (Operating Model), and a commercial model that monetizes mostly through balances and share of wallet, not feature fees (Pricing & Commercial).
A11: How to read the tabs
A12: Tab | B12: What it covers | C12: Note
A13: 1. Strategy on a Page | B13: The overarching view: diagnosis, five mandates, top bets, horizons, principles. | C13: Start here
A14: 2. Industry & Clients | B14: Deconstruction of the five Services business lines, client segments, and the value chain — with AI opportunity heat. | C14: The territory
A15: 3. Ontology | B15: The entity model (Client → Account → Instruction → Case…), the AI capability taxonomy, and the alignment rule every use case must pass. | C15: Your ontology-aligned view
A16: 4. Maturity Model | B16: 8 dimensions × 5 levels; where Services sits today (assessed), 12/24-month targets, what moves each dimension. | C16: Middle-of-the-pack baseline
A17: 5. Use-Case Portfolio | B17: 40 use cases across the five mandates, scored with editable weights; score and horizon are live formulas. | C17: Edit blue cells
A18: 6. Portfolio Summary | B18: Roll-up: counts and average scores by mandate and horizon; ranked top 12. | C18: Formulas only
A19: 7. Systems View | B19: Stocks & flows, reinforcing/balancing loops, leverage points, binding constraint, archetypes to avoid, delays. | C19: Your systems-oriented view
A20: 8. Operating Model & Governance | B20: How it is done at a global bank: pipeline stages, hub-and-spoke, control tiers, RACI, regulatory map for 30+ markets, model/vendor strategy. | C20: Domain confirmation
A21: 9. Pricing & Commercial | B21: AI for pricing (leakage, relationship pricing, deposit pricing) and pricing of AI (bundled / tiered / usage / value-share / balance-linked).
A22: 10. Business Case | B22: Illustrative value model with editable inputs and low/base/high sensitivities. Replace assumptions with internal baselines. | C22: Edit blue cells
A23: 11. Roadmap | B23: Nine workstreams × five periods (0–90 days to 36 months) with exit criteria.
A24: 12. Benchmarks & Peers | B24: What JPM, BNY, GS, BofA, HSBC, Wells, StanChart, DBS, DB, fintechs and networks have done; adoption benchmarks; copy/adapt/avoid. | C24: Dated, sourced
A25: 13. Panel Review | B25: Product leaders, strategists/business engineers, and systems thinkers: lens, endorsement, push-back, change requested. | C25: Frameworks applied, not quotes
A26: 14. Next Moves (AS) | B26: How to package this for the hiring manager, questions to ask, objections, extensions, verify-before-use list. | C26: For you, not for him
A27: 15. Sources | B27: Source list used across the workbook.
A29: Conventions
A30: Convention | B30: Meaning
A31: Blue text on yellow | B31: Editable input / assumption. Change these; everything downstream recalculates.
A32: Black text | B32: Formula or fixed content.
A33: [verify] | B33: A fact that could not be confirmed from a primary source, or that conflicts across sources. Check before sending.
A34: Scores | B34: 1 (low) to 5 (high). Control burden is inverted in the score (heavier controls lower the score).
A35: Attribution | B35: Strategy frameworks applied include the Business Engineering methodology (Analysis by The Business Engineer, Gennaro Cuofano, businessengineer.ai) alongside Rumelt, Helmer, Meadows, Goldratt, Beer, Cagan, Torres and others named on the Panel Review tab.
A36: Date | B36: Facts current to 22 Sep 2026. Citi financials per Q2 2026 earnings and FY2025 results.

Sheet Strategy on a Page
A1: Strategy on a Page — AI for Citi Services
A2: The whole argument on one tab. Everything else in the workbook is evidence for, or execution of, this page.
A4: Diagnosis → Guiding policy → Coherent action (Rumelt kernel)
A5: Element | B5: Content
A6: Diagnosis | B6: Services is the franchise leader (#1 TTS share 11.5%, FY25 revenue $21.3B, RoTCE 28.6%, >$1T deposits) inside a bank that is mid-pack in AI (Evident #12, down from #8; Leadership pillar 26th, Transparency 30th). Enterprise tooling is broadly deployed (180k+ employees, 40k developers with agents) but Services' value capture is activity-measured (prompts, users, hours), not P&L-measured, and client-facing AI is still in pilot (CitiDirect assistant). The constraint is the governed path from pilot to production — data lineage (consent-order remediation still open), tiered model-risk review for GenAI/agentic (now the bank's own responsibility under SR 26-2), and reusable components — not model capability or budget.
A7: Guiding policy | B7: Treat AI as a product line with a P&L, not a tool rollout. Build one industrialized pipeline (ontology → pattern → controls → production → measurement) and run all five mandates through it. Let client co-creation set demand; let balances and share of wallet — not feature fees — set the commercial model.
A8: Coherent actions | B8: (1) Stand up the Services AI product office with decision rights and a value ledger. (2) Ship the Now-wave bets in the Portfolio (E-01, E-10, I-01, I-03, C-05, P-01, E-03, C-01). (3) Fund the ontology/data foundation as a product with its own roadmap. (4) Convert MRM/controls into a tiered, pre-approved pattern library. (5) Launch a 10-client co-creation cohort per business line. (6) Publish quarterly value realized, internally and (selectively) externally.
A10: Five mandates — what good looks like
A11: Mandate | B11: Objective | C11: North-star metrics | D11: Top bets (IDs → Use-Case Portfolio) | E11: 12-month target | F11: Guardrail
A12: Internal (workforce) | B12: Every Services role has an AI-native workflow; the five Assist pillars run at scale across markets, not in pilots. | C12: Hours redeployed; % roles with AI workflow; adoption ≥ 85% | D12: I-01 Sales Assist/RFP · I-03 Ops Assist investigations · I-02 coverage briefing · I-06 Tech Assist | E12: 3 of 5 Assist pillars at scale in ≥ 20 markets; ≥ 100k hours/yr redeployed in Services (verify vs internal baseline) | F12: Human accountable for every client-facing output; no autonomous client communication
A13: Client (products) | B13: AI features clients stay for and pay for, co-created with named design partners, launched across 30+ markets on one global design. | C13: Client adoption; NPS on AI features; share of wallet; operating deposits | D13: C-05 CitiDirect AI assistant · C-01 cash-flow forecasting · C-04 predictive receivables · C-03 intelligent payment orchestration · C-02 liquidity optimization | E13: 2 client-facing AI products GA in ≥ 10 markets with ≥ 500 active clients; 10-client cohort per business line | F13: Explainability for any recommendation; no client decisioning without validated model + fairness review
A14: Pricing (commercial) | B14: Price to value and stop leakage; deal desk and coverage use one pricing intelligence layer. | C14: Fee realization %; price yield; win rate at target price; deposit beta accuracy | D14: P-01 fee leakage engine · P-02 relationship pricing · P-03 deposit pricing intelligence · P-06 attrition early warning | E14: Leakage recovery live for top-500 relationships; pricing recommendations in ≥ 50% of deal-desk decisions | F14: Conduct and antitrust review of pricing models; documented human override
A15: Product (how we build) | B15: Concept-to-commercialization cycle time halves; localization to 30+ markets is rules-driven from the ontology, not re-coded per market. | C15: Concept→GA cycle time; % specs AI-assisted; markets launched per release | D15: D-03 market localization agent · D-01 discovery synthesis · D-02 AI-assisted specs · D-05 client insight data product | E15: Cycle time −30%; localization backlog for one product cleared via ontology rules | F15: Product decisions remain with accountable PMs; AI drafts, humans decide
A16: Efficiency (ops & risk) | B16: Straight-through processing rises and exceptions fall; document-heavy and alert-heavy work is AI-first with human review by tier. | C16: Cost per transaction; STP rate; exceptions per million; alert dispositions per FTE | D16: E-01 IDP onboarding/KYC · E-10 Agent Assist at scale · E-03 payment repair · E-07 trade doc checking · E-02 screening triage | E16: Servicing effort −20% on 3M+ inquiries; onboarding doc review −80% in all markets; STP +3–5 pts on target flows | F16: Sanctions/AML models stay Tier-4 controlled; no auto-clearing of alerts without validated model
A18: Three horizons
A19: Horizon | B19: Focus | C19: Exit criteria
A20: Now (0–12 months) | B20: Industrialize what already works: IDP, Agent Assist, Ops Assist, Sales Assist, CitiDirect assistant, fee leakage, payment repair. Stand up the pipeline, ontology v1, value ledger, co-creation cohort. | C20: Prove P&L attribution on ≥ 5 use cases; publish first value report
A21: Next (12–24 months) | B21: Client products at scale: forecasting, receivables, orchestration, liquidity optimization advisor; pricing intelligence in deal desk; localization agent; screening triage under Tier-4 controls. | C21: ≥ 2 client products GA in 10+ markets; pricing recs in deal desk; cycle time −30%
A22: Later (24–36 months) | B22: Agentic treasury and agentic payments (Know-Your-Agent rails, Agent Pay for Machines / AP2-class protocols), client insight data products, regulatory reporting and regulatory-change automation, Issuer Services document intelligence. | C22: Services recognized as AI leader in transaction banking (Evident top-5 contribution); AI-attributed revenue disclosed
A24: Operating principles (the rules that resolve trade-offs)
A25: Principle | B25: What it means in practice
A26: 1. Ontology before models | B26: A use case that cannot name its golden-source entities and owners is not ready. Data readiness is scored, not assumed.
A27: 2. One governed pipeline | B27: Every use case — internal or client — flows through the same intake → tiering → validation → controls → monitoring path. Pre-approved patterns make the fast lane fast.
A28: 3. Reuse over rebuild | B28: Components (IDP, retrieval, evals, guardrails, agent runtime) are products with owners; use cases compose them.
A29: 4. Co-create with 10 before scaling to 10,000 | B29: Every client product has named design partners across segments and regions before GA.
A30: 5. Measure P&L, not pilots | B30: Value ledger with Finance sign-off; revenue, cost, risk, client metrics. Prompts and user counts are leading indicators only.
A31: 6. Global design, local controls | B31: Jurisdiction is a first-class entity; rules live in the ontology so 30+ markets are configuration, not code.

Sheet Industry & Clients
A1: Industry & Client Deconstruction — Citi Services
A2: Services = Treasury & Trade Solutions (Payments, Liquidity Management Services, Trade & Working Capital Solutions) + Securities Services (Investor Services, Issuer Services). Facts from Citi Investor Day (May 2026), Q2 2026 earnings, FY2025 results.
A4: A. Business lines — what they do, where the money is, where AI bites
A5: Business line | B5: What it does (platforms) | C5: Scale & position | D5: Economics | E5: Pain points (client / internal) | F5: AI heat (1–5) | G5: Why
A6: Payments | B6: Cross-border and domestic payments, USD clearing for ~300 bank clients in ~40 countries, commercial cards, Payments Express (live in 22 markets, up to 10M payments/day, ~40% of volume), Citi Token Services (5 locations, USD+EUR, ~$1B/day), WorldLink. | C6: #1 globally. FY25 cross-border value $416B (target $482B by 2028); Q2'26 $115B (+13%); USD clearing 177M instructions FY25; card spend $71B FY25; ~$6T processed daily across 180+ countries. | D6: Fees, FX margin, float/NII on transactional balances. Volume-led; unit cost falls with STP. | E6: Client: 'where is my payment', fraud (APP/beneficiary), rail choice (instant vs wire vs tokenized), ISO 20022 data underused. Internal: repairs/returns, sanctions false positives, investigations, 24/7 servicing across time zones. Emerging: agentic commerce (Mastercard Agent Pay, Visa Intelligent Commerce, Google AP2) needs 'Know Your Agent' rails. | F6: 5 | G6: Highest volume, richest structured data (ISO 20022), most exception-driven cost; agentic payments is the next platform shift.
A7: Liquidity Management Services (LMS) | B7: Account structures, pooling and sweeps (2,700+ clients, 80+ countries, ~$24T/yr swept), Real-Time Funding (2024), intercompany and multi-currency liquidity, interest optimization. | C7: #1. Average deposits >$1T (Q2'26 $1.017T, +19%). Target deposit CAGR ~3%. | D7: NII on operating balances dominates Services (FY25 NII $12.2B vs fees $3.1B). Deposit beta and balance mix are the economic engine. | E7: Client: forecasting accuracy, entity/currency structure optimization under local rules, intraday visibility. Internal: deposit classification (operating vs non-operating), pricing sensitivity, regulatory constraints per market. | F7: 4 | G7: Fewer transactions, but each recommendation moves balances — highest NII leverage per use case.
A8: Trade & Working Capital Solutions | B8: Supply-chain finance (~440k buyer–supplier relationships, ~$1T financing throughput in 2025, 'Nirvana' automated supplier onboarding), receivables and payables finance, letters of credit, guarantees, export finance. | C8: #1 in Trade. Document-intensive and credit-adjacent. | D8: Fees + financing margin + working-capital balances. | E8: Client: supplier onboarding speed, document friction (LC, invoices), DSO/DPO optimization. Internal: document checking, sanctions/dual-use screening, supplier risk scoring, compliance review across 160+ countries. | F8: 5 | G8: Unstructured documents everywhere → IDP and agentic checking with human sign-off; HSBC/ANZ/Lloyds/Microsoft PoC shows the pattern.
A9: Investor Services | B9: Custody (100+ markets; proprietary infrastructure in 62), fund services, middle office, Custody+ (Aug 2026: real-time settlement, liquidity sweeping, AI, digital assets; crypto custody targeted 2026). | C9: #4. AUC/AUA $35T (+22%); Securities Services FY25 revenue $5.9B (+15%); settlement volume +37%, cost/txn −25% cited. | D9: Asset-based and activity fees; scale economics in processing. | E9: Client: settlement fails, corporate-action timeliness, reporting. Internal: reconciliations, corporate actions (voluntary events already −92% processing time), client reporting narratives, onboarding. | F9: 4 | G9: Process-heavy back office where agents on reconciliations and corporate actions are proven (Goldman + Anthropic, BNY Eliza).
A10: Issuer Services | B10: Agency & trust, depositary receipts, escrow, structured-finance administration. | C10: #3. Smaller, document- and event-driven. | D10: Fees per deal / per event; long-dated mandates. | E10: Client: investor inquiries, event processing. Internal: indenture/agreement review, payment waterfalls, notices. | F10: 3 | G10: Document intelligence and Q&A; lower volume, lower priority but cheap to add once IDP exists.
A12: B. Client segments — jobs to be done and what they will value from AI
A13: Segment | B13: Jobs to be done | C13: What AI should do for them | D13: Willingness to pay | E13: Adoption readiness | F13: Co-creation candidate?
A14: Large multinational corporates (~80% of Fortune 500) | B14: Run global treasury across dozens of entities and currencies; optimize liquidity; pay and collect at scale; comply everywhere. | C14: Cash-flow forecasting, liquidity structure recommendations, intelligent routing, API/agentic treasury, anomaly alerts, faster onboarding of new entities. | D14: High for optimization that moves working capital; low for 'assistants' (expected free). | E14: High — sophisticated treasury teams, TMS/ERP integrated (Kyriba, SAP, HighRadius already pushing agents). | F14: Yes — 3–4 design partners per region; these are the RFP-driving references.
A15: Financial institutions (~98% of top-100 banks) | B15: USD clearing, correspondent banking, FX, custody; manage sanctions/fraud exposure on flows they don't originate. | C15: Screening quality, fraud/anomaly intelligence (federated with Swift), investigations speed, 24/7 clearing insight. | D15: Medium — pay for risk reduction and speed as part of clearing relationship. | E15: High operationally; cautious on data sharing. | F15: Yes — 2–3 clearing clients for fraud/investigations co-design.
A16: Public sector / sovereigns / IGOs | B16: Disbursements, collections, reserves; strict procurement and residency rules. | C16: Payment orchestration, reconciliation, reporting transparency. | D16: Low–medium; procurement-bound. | E16: Medium; long cycles. | F16: Selective.
A17: Commercial / mid-market (revenue 1.5x since 2022; '$100B addressable') | B17: Simpler treasury, fewer people; want 'done for me'. | C17: CitiDirect Commercial with embedded AI assistant, automated cash application, forecasting out-of-the-box, self-service onboarding. | D17: Medium — bundled tiers work; will pay for outcomes (DSO days). | E17: Medium; fastest-growing segment and most exposed to fintech alternatives (Stripe, Adyen, Tipalti). | F17: Yes — this is where a 'productized' AI tier can be tested first.
A18: Asset managers, asset owners, funds | B18: Custody, fund administration, data and reporting; settlement certainty. | C18: Settlement-fail prediction, corporate-action explainers, reporting narratives, data-as-a-product. | D18: Medium–high for data products. | E18: High. | F18: Yes — via Custody+ design partners.
A20: C. Value chain — where AI applies and how heavy the controls are
A21: Value-chain stage | B21: AI application | C21: Control intensity | D21: Use-case IDs
A22: 1. Sales, RFP, coverage | B22: Retrieve + generate (RFP responses, briefings), propensity models | C22: Low–medium | D22: I-01, I-02, P-04, P-06
A23: 2. Onboarding & KYC / implementation | B23: IDP (extract/classify), workflow agents, policy Q&A | C23: High (KYC/AML) | D23: E-01, I-05, C-08
A24: 3. Account & liquidity structuring | B24: Recommendation/optimization under jurisdictional rules | C24: Medium–high | D24: C-02, P-03
A25: 4. Instruction capture & enrichment | B25: Classification, repair, ISO 20022 enrichment | C25: Medium | D25: E-03, C-03
A26: 5. Screening (sanctions, fraud, AML) | B26: Anomaly detection, alert triage with explanations, federated learning | C26: Highest (Tier 4) | D26: E-02, E-08, C-06
A27: 6. Processing, clearing, settlement | B27: Predict fails, optimize routing, tokenized settlement | C27: High | D27: C-03, C-10
A28: 7. Exceptions, investigations, disputes | B28: Case copilots, agentic outreach drafting, root-cause clustering | C28: Medium | D28: I-03, E-04
A29: 8. Reconciliation & reporting | B29: Break resolution agents, narrative generation, regulatory reporting | C29: Medium–high | D29: E-05, E-06, E-09
A30: 9. Client servicing | B30: Conversational assistants (client and agent-facing), containment | C30: Medium | D30: C-05, E-10, I-04
A31: 10. Pricing & billing | B31: Leakage detection, price optimization, deposit pricing | C31: Medium (conduct) | D31: P-01, P-02, P-03, P-05
A32: 11. Product development & localization | B32: Discovery synthesis, spec drafting, rules-driven localization | C32: Low | D32: D-01…D-05

Sheet Ontology
A1: Ontology — the entity model AI strategy should be aligned to
A2: Object → properties → links → actions. Every use case must name the entities it reads and writes, the golden source, and the control tier. Jurisdiction is a first-class entity so 30+ markets become configuration, not code. Data-readiness scores are assessed, not measured — replace with the Services data catalog.
A4: A. Core entities (object types)
A5: Entity | B5: Key properties | C5: Links to | D5: Golden source (illustrative) | E5: AI patterns that act on it | F5: Use-case IDs | G5: Data readiness (1–5, assessed) | H5: Notes
A6: Client / Legal entity hierarchy | B6: Group → legal entity → operating unit; KYC status; segment; region | C6: Relationship, Account, Document, Case, Fee schedule | D6: KYC/CRM master; onboarding platform | E6: Retrieve, Predict (propensity/attrition), Recommend | F6: I-01, I-02, P-02, P-06, E-01 | G6: 3 | H6: Entity resolution across markets is the classic gap; consent-order data work is the forcing function.
A7: Relationship | B7: Products held, wallet share, coverage team, pricing agreement, revenue by product | C7: Client, Product, Fee schedule, Employee | D7: Revenue/pricing systems; CRM | E7: Predict, Recommend, Optimize | F7: P-02, P-03, P-06, I-02 | G7: 3 | H7: Revenue attribution by product is often reconstructed, not mastered.
A8: Account / Balance | B8: Account type, currency, jurisdiction, operating vs non-operating classification, intraday balance, sweep membership | C8: Client, Jurisdiction, Instruction, Forecast | D8: Core DDA/ledger; liquidity platform | E8: Forecast, Optimize, Detect | F8: C-01, C-02, P-03 | G8: 4 | H8: Balances are well-mastered; classification (operating/non-operating) is the model-relevant attribute to standardize.
A9: Product / Service | B9: Product code, features, market availability, pricing model, controls required | C9: Relationship, Fee schedule, Jurisdiction, Control | D9: Product catalog | E9: Retrieve, Generate (specs/docs) | F9: D-02, D-03, I-01 | G9: 3 | H9: Catalog completeness by market varies; localization agent depends on it.
A10: Instruction (payment / trade / settlement) | B10: ISO 20022 fields, rail, currency pair, urgency, status, repair history | C10: Account, Counterparty, Transaction, Case, Jurisdiction | D10: Payments engines; Payments Express; custody settlement | E10: Classify, Repair, Route, Predict (returns/fails) | F10: E-03, C-03, C-10, C-06 | G10: 4 | H10: ISO 20022 (CBPR+ complete Nov 2025) makes this the richest structured entity — exploit it.
A11: Transaction (posted) | B11: Amount, value date, fees applied, FX rate, linked instruction | C11: Account, Fee schedule, Instruction | D11: Ledgers | E11: Detect (leakage), Reconcile | F11: P-01, P-05, E-05 | G11: 4 | H11: Fee-applied vs fee-contracted comparison is the leakage engine.
A12: Counterparty / Beneficiary | B12: Identity, bank, country, risk rating, history of returns/fraud flags | C12: Instruction, Screening alert, Client | D12: Beneficiary master; screening systems | E12: Detect (anomaly), Classify (risk) | F12: C-06, E-02, E-08 | G12: 3 | H12: Beneficiary change and first-time payee are the highest-signal fraud features.
A13: Document | B13: Type (KYC doc, LC, invoice, contract, indenture), extracted fields, confidence, version, jurisdiction | C13: Client, Instruction, Case, Control | D13: Document platforms; IDP outputs | E13: Extract, Classify, Check (compliance), Generate (summaries) | F13: E-01, E-07, C-07, C-11 | G13: 3 | H13: IDP is proven (~80% cut); the missing piece is a canonical document-type taxonomy across business lines.
A14: Case / Exception | B14: Type (repair, investigation, dispute, break), SLA, root cause, resolution steps, outcome | C14: Instruction, Client, Employee, Inquiry | D14: Case management; gpi tracker | E14: Retrieve, Recommend next step, Generate outreach, Cluster root causes | F14: I-03, E-04, E-05, E-06 | G14: 4 | H14: Case text is the training corpus for Ops Assist; label root causes now.
A15: Inquiry / Interaction | B15: Channel, intent, sentiment, containment, linked case | C15: Client, Case, Employee | D15: Contact-center platform; CitiDirect | E15: Classify intent, Converse, Summarize | F15: C-05, E-10, D-01 | G15: 4 | H15: 3M+ inquiries/yr is the discovery goldmine for product (D-01).
A16: Fee schedule / Price | B16: Contracted fees, tiers, waivers, FX margins, effective dates, approvals | C16: Relationship, Product, Transaction | D16: Billing/pricing systems | E16: Detect (leakage), Optimize, Recommend | F16: P-01, P-02, P-04, P-05 | G16: 2 | H16: Usually the least-digitized entity (contracts in PDFs) — IDP on contracts unlocks P-01.
A17: Jurisdiction / Market | B17: Regulatory rules, formats, cut-offs, data-residency, product availability, local approvals | C17: Product, Instruction, Control, Account | D17: Regulatory inventory; product catalog | E17: Retrieve, Generate (localization rules), Monitor (reg change) | F17: D-03, I-07, C-02 | G17: 2 | H17: Encoding rules as data is the single biggest enabler of 'global design, local adaptation'.
... A21: Forecast / Scenario | B21: Horizon, entity scope, method, accuracy, assumptions | C21: Account, Client, Instruction | D21: Forecasting service (new) | E21: Predict, Simulate | F21: C-01, C-02, P-03 | G21: 2 | H21: New entity — define once and share between client forecasting and deposit pricing.
A23: B. AI capability taxonomy (the verbs)
A24: Capability | B24: What it does | C24: Typical technique | D24: Default control tier | E24: Example use cases | F24: Non-negotiable control
A25: Extract | B25: Turn documents/images into structured fields | C25: IDP (OCR + LLM), layout models | D25: Tier 1–2 (Tier 3 if feeding KYC decisions) | E25: E-01, E-07, C-07 | F25: Confidence thresholds; human review below threshold
A26: Classify / Route | B26: Assign intent, type, queue, risk band | C26: Classifiers, LLM few-shot | D26: Tier 1–3 | E26: E-03, E-10, E-02 | F26: Bias testing where routing affects client outcomes
A27: Predict / Forecast | B27: Estimate future balances, fails, returns, attrition | C27: Gradient boosting, time series, foundation-model features | D27: Tier 2–3 | E27: C-01, C-10, P-06 | F27: Traditional MRM validation applies (in scope of SR 26-2)
A28: Detect / Monitor | B28: Find anomalies, fraud, leakage, drift | C28: Anomaly detection, federated models | D28: Tier 3–4 | E28: C-06, E-08, P-01 | F28: False-positive budget; explanation for every alert
A29: Retrieve / Answer | B29: Ground answers in policies, cases, contracts | C29: RAG over governed corpora | D29: Tier 1–2 | E29: I-04, I-01, I-02 | F29: Entitlement-aware retrieval; citation required
A30: Generate | B30: Draft responses, specs, RFPs, narratives | C30: LLM with templates and evals | D30: Tier 1–2 | E30: I-01, D-02, C-10 | F30: Human edits and sends; no auto-send to clients
A31: Recommend / Decide (with human) | B31: Propose price, structure, next action | C31: Optimization + LLM explanation | D31: Tier 3 | E31: P-02, C-02, C-03 | F31: Documented override; conduct review for pricing
A32: Act (bounded agent) | B32: Execute multi-step tasks within limits | C32: Agent runtime with tools, guardrails, kill switch | D32: Tier 3–4 | E32: E-04, E-05, I-06, C-09 | F32: Action allow-lists, spend/volume caps, post-hoc review, full trace
A33: Simulate / Optimize | B33: Scenario analysis for liquidity, routing, pricing | C33: OR/optimization + ML | D33: Tier 3 | E33: C-02, C-03, P-03 | F33: Assumptions logged; sensitivity shown to user
A35: C. Alignment rule — the test every use case must pass
A36: Use case = (Entities read/written) × (Capability) × (Control tier) × (Accountable owner) × (Golden source confirmed). If any factor is blank, the use case goes to the data/ontology backlog, not the build backlog. This one rule converts 'AI ideas' into a manageable pipeline and is what separates the 5% of enterprises capturing value at scale (BCG, Sep 2025) from the 60% seeing minimal gains.
A37: How it is done elsewhere: banks are converging on object-oriented operational ontologies (Palantir-style object/link/action models are in production at several large FIs), knowledge graphs for KYC/AML entity resolution, and ISO 20022 as the de facto shared payments ontology. Citi's data-lineage remediation under the remaining consent orders is the natural funding vehicle: lineage work and ontology work are the same work, described for two audiences.

Sheet Maturity Model
A1: AI Maturity Model — where Services sits and what moves it
A2: 8 dimensions × 5 levels. 'Today' is an outside-in assessment from public evidence (Investor Day May 2026, Q2'26 call, Evident 2025, press); treat as a hypothesis to validate with the hiring manager. Average ≈ 2.5 = middle of the pack, which matches Evident #12.
A4: Dimension | B4: L1 Exploring | C4: L2 Piloting | D4: L3 Scaling pockets | E4: L4 Industrialized | F4: L5 AI-native | G4: Today (1–5) | H4: Evidence for today | I4: 12-mo target | J4: 24-mo target | K4: What moves the needle
A5: Strategy & value governance | B5: Ad-hoc ideas; no owner | C5: Named pillars and pipeline; activity metrics | D5: Business-line owners; some P&L attribution | E5: Value ledger with Finance sign-off; portfolio managed by ROI | F5: AI P&L disclosed; strategy bets sequenced by value | G5: 3 | H5: Five Assist pillars, 50+ use-case pipeline, EMT sponsorship; but no disclosed $ value (JPM discloses ~$2B); Evident Leadership pillar 26th, Transparency 30th. | I5: 4 | J5: 4 | K5: This role: value ledger, quarterly value report, decision rights. Publish selectively (Transparency pillar).
A6: Data & ontology | B6: Siloed, undocumented | C6: Lineage projects; some catalogs | D6: Shared entities for priority domains | E6: Ontology as product; golden sources enforced | F6: Real-time, entitlement-aware, self-describing data | G6: 2 | H6: Consent-order data/regulatory-reporting remediation still open (Mason, Dec 2025); ISO 20022 richness available; Platforms & Data Solutions exists in Services. | I6: 3 | J6: 4 | K6: Fund ontology v1 for 8 entities (Ontology tab); merge with lineage program; readiness score gates the pipeline.
A7: Platform & tooling | B7: Individual tools | C7: Enterprise assistants deployed | D7: Multi-model access; agent pilots; dev agents | E7: Reusable components (IDP, RAG, evals, agent runtime) with owners | F7: Composable AI platform; cost/inference governed | G7: 3 | H7: Enterprise stack strong (Gemini + Anthropic + Llama; Stylus Workspaces agentic pilot; Copilot/Devin to 40k devs; ~$2B/yr Services platform spend) but Services-specific reusable components not evident. | I7: 4 | J7: 4 | K7: Component roadmap with product owners; cost-per-run telemetry; abstraction layer for model portability.
A8: Model risk & controls | B8: Traditional MRM only | C8: GenAI guidance drafted; case-by-case review | D8: Tiered regime; pre-approved patterns for low tiers | E8: Continuous evals/monitoring; agent controls (allow-lists, kill switch) | F8: Automated evidence; regulator-ready lineage per use case | G8: 3 | H8: Mature MRM culture (SR 11-7 heritage; Services AI risk roles cite SHAP/LIME, AI risk registers). SR 26-2 (Apr 2026) puts GenAI/agentic outside MRM scope → bank's own governance must fill it. | I8: 4 | J8: 4 | K8: Joint MRM–Services pod; tiered control library; eval harness as shared component; publish validation SLAs.
A9: Talent & ways of working | B9: Enthusiasts | C9: Broad training; champions network | D9: Business teams redesign workflows | E9: Roles redefined; AI fluency in performance criteria | F9: AI-native org design; super-ICs | G9: 3 | H9: 180k+ employees on tools, ~70–90% adoption, mandatory prompt training, 4,000 accelerators; but Head of AI left after 7 months (Apr 2026) and AI CoE lead departing (Oct 2026). | I9: 3 | J9: 4 | K9: Workflow redesign (the #1 differentiator of McKinsey 'high performers': 73% vs 25%); stable business-line AI leadership.
A10: Operating model | B10: Central lab | C10: Hub with informal spokes | D10: Business-line AI product leads with budgets | E10: Hub-and-spoke with shared pipeline and decision rights | F10: Federated by default; hub sets standards only | G10: 2 | H10: Firmwide AI org reorganized May 2026 (Group Head of AI; Office of AI Strategy); Services business-line AI roles (this one) being hired now. | I10: 3 | J10: 4 | K10: Define decision rights (Operating Model tab); RACI per use case; one intake.
A11: Client co-creation & commercialization | B11: No client-facing AI | C11: Pilots with a few clients | D11: Named design partners; first GA product | E11: Cohorts per business line; pricing tested; GTM in waves | F11: AI features in every RFP; clients build on Citi's agent rails | G11: 2 | H11: CitiDirect AI assistant in client pilot (+50% containment); Sales Assist internal; no client-facing AI product at BofA CashPro Forecasting scale (3,000+ clients). | I11: 3 | J11: 4 | K11: 10-client cohort per business line; forecasting + receivables GA; pricing experiments in Commercial segment.
A12: Measurement & value realization | B12: Anecdotes | C12: Activity metrics (users, prompts, hours) | D12: Use-case KPIs; some P&L attribution | E12: Value ledger reconciled by Finance; leading and lagging indicators | F12: AI value in external disclosures and targets | G12: 2 | H12: Metrics cited are users/prompts/hours (100k dev hours/wk firmwide); Services cites % effort reductions but no $ figure. | I12: 3 | J12: 4 | K12: Business Case tab as the template; Finance co-owns; report quarterly.
A13: Overall (average) | G13: =ROUND(AVERAGE(G5:G12),2) -> 2.5 | H13: Middle of the pack ≈ 2.5. Target ≈3.4 in 12 months, 4.0 in 24 months. | I13: =ROUND(AVERAGE(I5:I12),2) -> 3.38 | J13: =ROUND(AVERAGE(J5:J12),2) -> 4
A15: Reading the model
A16: Why this matters for the strategy: the two lowest dimensions (Data & ontology; Client co-creation; Measurement; Operating model — all at L2) are exactly the ones a business-line AI product leader can move without new technology. Platform and talent are already L3 thanks to the enterprise program. The plan therefore over-invests in the L2 dimensions during the first 12 months — that is where the score, and the P&L, moves.

Sheet Use-Case Portfolio
A1: Use-Case Portfolio — 40 use cases across five mandates, scored
A2: Score = weighted 1–5 ratings scaled to 100 (control burden inverted). Horizon = Now if score ≥ Now threshold and time-to-value ≤ max; Next if score ≥ Next threshold; else Later. Ratings are outside-in judgments — run this as a workshop with the business line and replace them.
A3: Scoring weights & thresholds (edit blue cells) | B3: Value | C3: 0.3 | D3: Feasibility | E3: 0.2 | F3: Data readiness | G3: 0.15 | H3: Control ease | I3: 0.15 | J3: Strategic fit | K3: 0.2 | L3: =SUM(C3,E3,G3,I3,K3) -> 1 | M3: Now: score ≥ | N3: 77 | O3: Next: score ≥ | P3: 68 | Q3: Now: max TTV (mo) | R3: 9
A5: ID | B5: Mandate | C5: Business line | D5: Value-chain stage | E5: Use case | F5: What it does | G5: AI pattern | H5: Ontology entities | I5: Value type | J5: Value (1–5) | K5: Feasibility (1–5) | L5: Data readiness (1–5) | M5: Control burden (1–5, 5=heaviest) | N5: Time-to-value (months) | O5: Strategic fit (1–5) | P5: Score (0–100) | Q5: Horizon | R5: Peer precedent | S5: Primary KPI | T5: Owner (function) | U5: Rank helper | V5: Rank
A6: I-01 | B6: Internal | C6: All (Sales) | D6: 1. Sales, RFP, coverage | E6: Sales Assist / RFP response engine | F6: Drafts RFP and proposal responses from approved product, pricing and control content; tracks ~10k complex engagements/yr. | G6: Retrieve + Generate | H6: Client, Product, Document, Fee schedule | I6: Revenue (win rate), Cost | J6: 4 | K6: 5 | L6: 4 | M6: 2 | N6: 6 | O6: 5 | P6: =ROUND((J6*$C$3+K6*$E$3+L6*$G$3+(6-M6)*$I$3+O6*$K$3)/$L$3*20,1) -> 88 | Q6: =IF(AND(P6>=$N$3,N6<=$R$3),"Now (0-12m)",IF(P6>=$P$3,"Next (12-24m)","Later (24-36m)")) -> Now (0-12m) | R6: Citi Services already targets this (Investor Day 2026); StanChart SC GPT; GS sales enablement | S6: RFP cycle time; win rate; hours per RFP | T6: Sales enablement + AI product lead | U6: =P6+ROW()/100000 -> 88.00006 | V6: =RANK(U6,$U$6:$U$45,0) -> 4
A7: I-02 | B7: Internal | C7: All (Coverage) | D7: 1. Sales, RFP, coverage | E7: Coverage briefing agent | F7: Pre-meeting brief: balances, flows, open cases, pricing, news; next-best-action suggestions. | G7: Retrieve + Generate + Predict | H7: Client, Relationship, Account, Case | I7: Revenue (share of wallet) | J7: 4 | K7: 4 | L7: 3 | M7: 2 | N7: 6 | O7: 4 | P7: =ROUND((J7*$C$3+K7*$E$3+L7*$G$3+(6-M7)*$I$3+O7*$K$3)/$L$3*20,1) -> 77 | Q7: =IF(AND(P7>=$N$3,N7<=$R$3),"Now (0-12m)",IF(P7>=$P$3,"Next (12-24m)","Later (24-36m)")) -> Now (0-12m) | R7: DBS credit-memo agents (1,500 bankers, ≥30% time saved); Wells Fargo Agentspace | S7: Prep time per meeting; cross-sell actions taken | T7: Coverage + AI product lead | U7: =P7+ROW()/100000 -> 77.00007 | V7: =RANK(U7,$U$6:$U$45,0) -> 22
A8: I-03 | B8: Internal | C8: Payments | D8: 7. Exceptions, investigations | E8: Ops Assist — investigations & inquiry copilot | F8: Resolves 'where is my payment' with gpi tracking, case history, and drafted client responses; suggests next step. | G8: Retrieve + Generate + Recommend | H8: Instruction, Case, Inquiry, Client | I8: Cost, Client experience | J8: 5 | K8: 4 | L8: 4 | M8: 2 | N8: 6 | O8: 5 | P8: =ROUND((J8*$C$3+K8*$E$3+L8*$G$3+(6-M8)*$I$3+O8*$K$3)/$L$3*20,1) -> 90 | Q8: =IF(AND(P8>=$N$3,N8<=$R$3),"Now (0-12m)",IF(P8>=$P$3,"Next (12-24m)","Later (24-36m)")) -> Now (0-12m) | R8: JPM Payments: manual exceptions −50% while volumes +50% | S8: Handle time; cases per FTE; client SLA hit rate | T8: Payments Ops | U8: =P8+ROW()/100000 -> 90.00008 | V8: =RANK(U8,$U$6:$U$45,0) -> 3
A9: I-04 | B9: Internal | C9: All | D9: 9. Client servicing | E9: Policy & procedure Q&A for ops in 90+ markets | F9: Extends Citi Assist with Services procedures, cut-offs and market rules; entitlement-aware. | G9: Retrieve | H9: Control, Jurisdiction, Product, Employee | I9: Cost, Risk | J9: 3 | K9: 5 | L9: 4 | M9: 1 | N9: 3 | O9: 3 | P9: =ROUND((J9*$C$3+K9*$E$3+L9*$G$3+(6-M9)*$I$3+O9*$K$3)/$L$3*20,1) -> 77 | Q9: =IF(AND(P9>=$N$3,N9<=$R$3),"Now (0-12m)",IF(P9>=$P$3,"Next (12-24m)","Later (24-36m)")) -> Now (0-12m) | R9: Citi Assist (enterprise), BofA Erica for Employees (IT calls −50%) | S9: Deflected escalations; time to answer | T9: Ops COO | U9: =P9+ROW()/100000 -> 77.00009 | V9: =RANK(U9,$U$6:$U$45,0) -> 21
A10: I-05 | B10: Internal | C10: All | D10: 2. Onboarding & implementation | E10: Implementation PM copilot | F10: Builds client implementation plans, document checklists and status updates from templates and case history. | G10: Retrieve + Generate | H10: Client, Document, Product, Jurisdiction | I10: Cost, Revenue (time-to-revenue) | J10: 3 | K10: 4 | L10: 3 | M10: 2 | N10: 9 | O10: 4 | P10: =ROUND((J10*$C$3+K10*$E$3+L10*$G$3+(6-M10)*$I$3+O10*$K$3)/$L$3*20,1) -> 71 | Q10: =IF(AND(P10>=$N$3,N10<=$R$3),"Now (0-12m)",IF(P10>=$P$3,"Next (12-24m)","Later (24-36m)")) -> Next (12-24m) | R10: GS client onboarding agents with Anthropic | S10: Implementation cycle time; PM capacity | T10: Implementations | U10: =P10+ROW()/100000 -> 71.0001 | V10: =RANK(U10,$U$6:$U$45,0) -> 32
A11: I-06 | B11: Internal | C11: All (Tech) | D11: 11. Product & localization | E11: Tech Assist — developer agents on Services platforms | F11: Copilot/Devin-class agents for code, tests, upgrades and legacy remediation across Services' estate. | G11: Act (bounded) + Generate | H11: Model/Agent, Product | I11: Cost, Speed | J11: 4 | K11: 5 | L11: 4 | M11: 2 | N11: 3 | O11: 4 | P11: =ROUND((J11*$C$3+K11*$E$3+L11*$G$3+(6-M11)*$I$3+O11*$K$3)/$L$3*20,1) -> 84 | Q11: =IF(AND(P11>=$N$3,N11<=$R$3),"Now (0-12m)",IF(P11>=$P$3,"Next (12-24m)","Later (24-36m)")) -> Now (0-12m) | R11: Citi: 40k devs, Copilot 5–15%, Devin 2–20x on patches; Services cites 30–40% dev productivity | S11: Throughput per dev; change lead time; defect rate | T11: Services Technology | U11: =P11+ROW()/100000 -> 84.00011 | V11: =RANK(U11,$U$6:$U$45,0) -> 9
A12: I-07 | B12: Internal | C12: All | D12: 11. Product & localization | E12: Regulatory-change intelligence agent | F12: Monitors rule changes in 90+ markets, summarizes, maps to products/controls, opens tasks. | G12: Monitor + Retrieve + Generate | H12: Jurisdiction, Control, Product | I12: Risk, Cost | J12: 4 | K12: 3 | L12: 2 | M12: 3 | N12: 12 | O12: 4 | P12: =ROUND((J12*$C$3+K12*$E$3+L12*$G$3+(6-M12)*$I$3+O12*$K$3)/$L$3*20,1) -> 67 | Q12: =IF(AND(P12>=$N$3,N12<=$R$3),"Now (0-12m)",IF(P12>=$P$3,"Next (12-24m)","Later (24-36m)")) -> Later (24-36m) | R12: Common in Compliance (multiple banks); ties to I-07/D-03 localization | S12: Reg changes triaged within SLA; rework avoided | T12: Compliance + Product | U12: =P12+ROW()/100000 -> 67.00012 | V12: =RANK(U12,$U$6:$U$45,0) -> 36
A13: C-01 | B13: Client | C13: LMS | D13: 3. Liquidity structuring | E13: Cash-flow forecasting for treasurers (in CitiDirect) | F13: ML forecasts of balances and flows by entity/currency with accuracy tracking; feeds liquidity decisions. | G13: Predict / Forecast | H13: Account, Instruction, Forecast, Client | I13: Deposits (NII), Retention | J13: 5 | K13: 4 | L13: 4 | M13: 3 | N13: 9 | O13: 5 | P13: =ROUND((J13*$C$3+K13*$E$3+L13*$G$3+(6-M13)*$I$3+O13*$K$3)/$L$3*20,1) -> 87 | Q13: =IF(AND(P13>=$N$3,N13<=$R$3),"Now (0-12m)",IF(P13>=$P$3,"Next (12-24m)","Later (24-36m)")) -> Now (0-12m) | R13: BofA CashPro Forecasting: 3,000+ clients, 250k client hours saved; JPM cites 20–30% accuracy uplift | S13: Active clients; forecast MAPE; operating balances of users | T13: LMS Product | U13: =P13+ROW()/100000 -> 87.00013 | V13: =RANK(U13,$U$6:$U$45,0) -> 7
A14: C-02 | B14: Client | C14: LMS | D14: 3. Liquidity structuring | E14: Liquidity structure optimization advisor | F14: Recommends pooling/sweep/intercompany structures across entities, currencies and jurisdictional constraints. | G14: Recommend + Optimize | H14: Account, Jurisdiction, Forecast, Product | I14: Deposits (NII), Fees | J14: 5 | K14: 3 | L14: 3 | M14: 3 | N14: 12 | O14: 5 | P14: =ROUND((J14*$C$3+K14*$E$3+L14*$G$3+(6-M14)*$I$3+O14*$K$3)/$L$3*20,1) -> 80 | Q14: =IF(AND(P14>=$N$3,N14<=$R$3),"Now (0-12m)",IF(P14>=$P$3,"Next (12-24m)","Later (24-36m)")) -> Next (12-24m) | R14: No scaled peer product yet — white space; Kyriba/HighRadius moving from TMS side | S14: Structures recommended/adopted; balances consolidated | T14: LMS Product | U14: =P14+ROW()/100000 -> 80.00014 | V14: =RANK(U14,$U$6:$U$45,0) -> 16
A15: C-03 | B15: Client | C15: Payments | D15: 4./6. Instruction & processing | E15: Intelligent payment orchestration / routing | F15: Chooses rail (instant, wire, Payments Express, Token Services) by cost, speed, FX, success probability; explains choice. | G15: Recommend + Optimize + Predict | H15: Instruction, Jurisdiction, Counterparty, Fee schedule | I15: Fees, Client experience, Cost | J15: 5 | K15: 3 | L15: 4 | M15: 4 | N15: 12 | O15: 5 | P15: =ROUND((J15*$C$3+K15*$E$3+L15*$G$3+(6-M15)*$I$3+O15*$K$3)/$L$3*20,1) -> 80 | Q15: =IF(AND(P15>=$N$3,N15<=$R$3),"Now (0-12m)",IF(P15>=$P$3,"Next (12-24m)","Later (24-36m)")) -> Next (12-24m) | R15: Named in the JD; Stripe/Adyen do this for merchants; JPM agentic payments | S15: Straight-through rate; cost per payment; client NPS | T15: Payments Product | U15: =P15+ROW()/100000 -> 80.00015 | V15: =RANK(U15,$U$6:$U$45,0) -> 15
A16: C-04 | B16: Client | C16: Trade & WC / Payments | D16: 8. Reconciliation | E16: Predictive receivables & cash application | F16: Matches remittances to invoices, predicts payer behavior and DSO; automates cash application. | G16: Extract + Classify + Predict | H16: Transaction, Document, Counterparty, Client | I16: Fees, Working-capital balances | J16: 4 | K16: 4 | L16: 3 | M16: 3 | N16: 9 | O16: 5 | P16: =ROUND((J16*$C$3+K16*$E$3+L16*$G$3+(6-M16)*$I$3+O16*$K$3)/$L$3*20,1) -> 78 | Q16: =IF(AND(P16>=$N$3,N16<=$R$3),"Now (0-12m)",IF(P16>=$P$3,"Next (12-24m)","Later (24-36m)")) -> Now (0-12m) | R16: Named in the JD; HighRadius (186 agents), SAP Taulia working-capital agent | S16: Auto-match rate; DSO days improved; clients live | T16: Receivables Product | U16: =P16+ROW()/100000 -> 78.00016 | V16: =RANK(U16,$U$6:$U$45,0) -> 17
A17: C-05 | B17: Client | C17: All (CitiDirect) | D17: 9. Client servicing | E17: CitiDirect AI assistant — scale to 30 markets | F17: Conversational servicing and navigation inside CitiDirect; escalates to humans with full context. | G17: Converse + Retrieve | H17: Inquiry, Client, Account, Instruction | I17: Cost, Client experience | J17: 4 | K17: 5 | L17: 4 | M17: 3 | N17: 6 | O17: 5 | P17: =ROUND((J17*$C$3+K17*$E$3+L17*$G$3+(6-M17)*$I$3+O17*$K$3)/$L$3*20,1) -> 85 | Q17: =IF(AND(P17>=$N$3,N17<=$R$3),"Now (0-12m)",IF(P17>=$P$3,"Next (12-24m)","Later (24-36m)")) -> Now (0-12m) | R17: Citi pilot: +50% containment; BofA Erica 3.2B interactions | S17: Containment; CSAT; markets live | T17: Digital Channels | U17: =P17+ROW()/100000 -> 85.00017 | V17: =RANK(U17,$U$6:$U$45,0) -> 8
... A45: E-11 | B45: Efficiency | C45: All (Tech) | D45: 11. Platform simplification | E45: Legacy modernization agents | F45: Agents document, test and migrate legacy Services applications (384 apps retired firmwide in 2025). | G45: Act (bounded) + Generate | H45: Model/Agent, Product | I45: Cost | J45: 4 | K45: 4 | L45: 4 | M45: 2 | N45: 12 | O45: 3 | P45: =ROUND((J45*$C$3+K45*$E$3+L45*$G$3+(6-M45)*$I$3+O45*$K$3)/$L$3*20,1) -> 76 | Q45: =IF(AND(P45>=$N$3,N45<=$R$3),"Now (0-12m)",IF(P45>=$P$3,"Next (12-24m)","Later (24-36m)")) -> Next (12-24m) | R45: Citi Devin usage on upgrades/rewrites | S45: Apps retired; run-cost saved | T45: Services Technology | U45: =P45+ROW()/100000 -> 76.00045 | V45: =RANK(U45,$U$6:$U$45,0) -> 23
A47: Mandate codes: I = Internal (workforce), C = Client (products), P = Pricing (commercial), D = Product (how we build), E = Efficiency (operations & risk). Control burden 5 = Tier-4 (client decisioning / sanctions-AML); 1 = Tier-1 assist. Peer precedents dated 2025–2026; see Benchmarks & Peers for sources.

Sheet Portfolio Summary
A1: Portfolio Summary — roll-up of the scored portfolio (all formulas)
A2: Recalculates from the Use-Case Portfolio. Use it to check mix: the base of the pyramid (productivity/efficiency) should dominate Now; strategic client bets should dominate Next; agentic/platform bets sit in Later.
A4: A. By mandate
A5: Mandate | B5: # use cases | C5: Avg score | D5: # Now (0-12m) | E5: # Next (12-24m) | F5: # Later (24-36m)
A6: Internal | B6: =COUNTIF('Use-Case Portfolio'!$B$6:$B$45,A6) -> 7 | C6: =IFERROR(ROUND(AVERAGEIF('Use-Case Portfolio'!$B$6:$B$45,A6,'Use-Case Portfolio'!$P$6:$P$45),1),0) -> 79.1 | D6: =COUNTIFS('Use-Case Portfolio'!$B$6:$B$45,A6,'Use-Case Portfolio'!$Q$6:$Q$45,"Now*") -> 5 | E6: =COUNTIFS('Use-Case Portfolio'!$B$6:$B$45,A6,'Use-Case Portfolio'!$Q$6:$Q$45,"Next*") -> 1 | F6: =COUNTIFS('Use-Case Portfolio'!$B$6:$B$45,A6,'Use-Case Portfolio'!$Q$6:$Q$45,"Later*") -> 1
A7: Client | B7: =COUNTIF('Use-Case Portfolio'!$B$6:$B$45,A7) -> 11 | C7: =IFERROR(ROUND(AVERAGEIF('Use-Case Portfolio'!$B$6:$B$45,A7,'Use-Case Portfolio'!$P$6:$P$45),1),0) -> 75.2 | D7: =COUNTIFS('Use-Case Portfolio'!$B$6:$B$45,A7,'Use-Case Portfolio'!$Q$6:$Q$45,"Now*") -> 3 | E7: =COUNTIFS('Use-Case Portfolio'!$B$6:$B$45,A7,'Use-Case Portfolio'!$Q$6:$Q$45,"Next*") -> 6 | F7: =COUNTIFS('Use-Case Portfolio'!$B$6:$B$45,A7,'Use-Case Portfolio'!$Q$6:$Q$45,"Later*") -> 2
A8: Pricing | B8: =COUNTIF('Use-Case Portfolio'!$B$6:$B$45,A8) -> 6 | C8: =IFERROR(ROUND(AVERAGEIF('Use-Case Portfolio'!$B$6:$B$45,A8,'Use-Case Portfolio'!$P$6:$P$45),1),0) -> 78 | D8: =COUNTIFS('Use-Case Portfolio'!$B$6:$B$45,A8,'Use-Case Portfolio'!$Q$6:$Q$45,"Now*") -> 2 | E8: =COUNTIFS('Use-Case Portfolio'!$B$6:$B$45,A8,'Use-Case Portfolio'!$Q$6:$Q$45,"Next*") -> 4 | F8: =COUNTIFS('Use-Case Portfolio'!$B$6:$B$45,A8,'Use-Case Portfolio'!$Q$6:$Q$45,"Later*") -> 0
A9: Product | B9: =COUNTIF('Use-Case Portfolio'!$B$6:$B$45,A9) -> 5 | C9: =IFERROR(ROUND(AVERAGEIF('Use-Case Portfolio'!$B$6:$B$45,A9,'Use-Case Portfolio'!$P$6:$P$45),1),0) -> 71.2 | D9: =COUNTIFS('Use-Case Portfolio'!$B$6:$B$45,A9,'Use-Case Portfolio'!$Q$6:$Q$45,"Now*") -> 2 | E9: =COUNTIFS('Use-Case Portfolio'!$B$6:$B$45,A9,'Use-Case Portfolio'!$Q$6:$Q$45,"Next*") -> 1 | F9: =COUNTIFS('Use-Case Portfolio'!$B$6:$B$45,A9,'Use-Case Portfolio'!$Q$6:$Q$45,"Later*") -> 2
A10: Efficiency | B10: =COUNTIF('Use-Case Portfolio'!$B$6:$B$45,A10) -> 11 | C10: =IFERROR(ROUND(AVERAGEIF('Use-Case Portfolio'!$B$6:$B$45,A10,'Use-Case Portfolio'!$P$6:$P$45),1),0) -> 78.5 | D10: =COUNTIFS('Use-Case Portfolio'!$B$6:$B$45,A10,'Use-Case Portfolio'!$Q$6:$Q$45,"Now*") -> 6 | E10: =COUNTIFS('Use-Case Portfolio'!$B$6:$B$45,A10,'Use-Case Portfolio'!$Q$6:$Q$45,"Next*") -> 4 | F10: =COUNTIFS('Use-Case Portfolio'!$B$6:$B$45,A10,'Use-Case Portfolio'!$Q$6:$Q$45,"Later*") -> 1
A11: Total | B11: =SUM(B6:B10) -> 40 | C11: =ROUND(AVERAGE('Use-Case Portfolio'!$P$6:$P$45),1) -> 76.7 | D11: =SUM(D6:D10) -> 18 | E11: =SUM(E6:E10) -> 16 | F11: =SUM(F6:F10) -> 6
A13: B. Mix check vs recommended allocation (share of use cases)
A14: Horizon | B14: Actual # | C14: Actual % | D14: Recommended % | E14: Gap (pts) | F14: Read
A15: Now (0-12m) | B15: =D11 -> 18 | C15: =IFERROR(B15/$B$11,0) -> 0.45 | D15: 0.45 | E15: =(C15-D15)*100 -> 0 | F15: Productivity and efficiency base — proven patterns, fast value
A16: Next (12-24m) | B16: =E11 -> 16 | C16: =IFERROR(B16/$B$11,0) -> 0.4 | D16: 0.4 | E16: =(C16-D16)*100 -> 0 | F16: Client products and pricing intelligence — the differentiation layer
A17: Later (24-36m) | B17: =F11 -> 6 | C17: =IFERROR(B17/$B$11,0) -> 0.15 | D17: 0.15 | E17: =(C17-D17)*100 -> 0 | F17: Agentic rails, data products, structural bets — convex, small position
A18: Recommended split adapts the AI Implementation Pyramid (≈70/15/10/5 of budget across productivity / workflow automation / strategic advantage / R&D bets) to a use-case count. Budget share will skew more to Now than count share does, because Now items are cheaper per unit.
A20: C. Top 12 by score (ranked; ties broken by row order)
A21: Rank | B21: ID | C21: Use case | D21: Mandate | E21: Score | F21: Horizon
A22: 1 | B22: =INDEX('Use-Case Portfolio'!$A$6:$A$45,MATCH(A22,'Use-Case Portfolio'!$V$6:$V$45,0)) -> E-10 | C22: =INDEX('Use-Case Portfolio'!$E$6:$E$45,MATCH(A22,'Use-Case Portfolio'!$V$6:$V$45,0)) -> CitiService Agent Assist — 6,000 agents / 72 countries | D22: =INDEX('Use-Case Portfolio'!$B$6:$B$45,MATCH(A22,'Use-Case Portfolio'!$V$6:$V$45,0)) -> Efficiency | E22: =INDEX('Use-Case Portfolio'!$P$6:$P$45,MATCH(A22,'Use-Case Portfolio'!$V$6:$V$45,0)) -> 94 | F22: =INDEX('Use-Case Portfolio'!$Q$6:$Q$45,MATCH(A22,'Use-Case Portfolio'!$V$6:$V$45,0)) -> Now (0-12m)
A23: 2 | B23: =INDEX('Use-Case Portfolio'!$A$6:$A$45,MATCH(A23,'Use-Case Portfolio'!$V$6:$V$45,0)) -> E-01 | C23: =INDEX('Use-Case Portfolio'!$E$6:$E$45,MATCH(A23,'Use-Case Portfolio'!$V$6:$V$45,0)) -> IDP for onboarding/KYC documents — all markets | D23: =INDEX('Use-Case Portfolio'!$B$6:$B$45,MATCH(A23,'Use-Case Portfolio'!$V$6:$V$45,0)) -> Efficiency | E23: =INDEX('Use-Case Portfolio'!$P$6:$P$45,MATCH(A23,'Use-Case Portfolio'!$V$6:$V$45,0)) -> 91 | F23: =INDEX('Use-Case Portfolio'!$Q$6:$Q$45,MATCH(A23,'Use-Case Portfolio'!$V$6:$V$45,0)) -> Now (0-12m)
A24: 3 | B24: =INDEX('Use-Case Portfolio'!$A$6:$A$45,MATCH(A24,'Use-Case Portfolio'!$V$6:$V$45,0)) -> I-03 | C24: =INDEX('Use-Case Portfolio'!$E$6:$E$45,MATCH(A24,'Use-Case Portfolio'!$V$6:$V$45,0)) -> Ops Assist — investigations & inquiry copilot | D24: =INDEX('Use-Case Portfolio'!$B$6:$B$45,MATCH(A24,'Use-Case Portfolio'!$V$6:$V$45,0)) -> Internal | E24: =INDEX('Use-Case Portfolio'!$P$6:$P$45,MATCH(A24,'Use-Case Portfolio'!$V$6:$V$45,0)) -> 90 | F24: =INDEX('Use-Case Portfolio'!$Q$6:$Q$45,MATCH(A24,'Use-Case Portfolio'!$V$6:$V$45,0)) -> Now (0-12m)
A25: 4 | B25: =INDEX('Use-Case Portfolio'!$A$6:$A$45,MATCH(A25,'Use-Case Portfolio'!$V$6:$V$45,0)) -> I-01 | C25: =INDEX('Use-Case Portfolio'!$E$6:$E$45,MATCH(A25,'Use-Case Portfolio'!$V$6:$V$45,0)) -> Sales Assist / RFP response engine | D25: =INDEX('Use-Case Portfolio'!$B$6:$B$45,MATCH(A25,'Use-Case Portfolio'!$V$6:$V$45,0)) -> Internal | E25: =INDEX('Use-Case Portfolio'!$P$6:$P$45,MATCH(A25,'Use-Case Portfolio'!$V$6:$V$45,0)) -> 88 | F25: =INDEX('Use-Case Portfolio'!$Q$6:$Q$45,MATCH(A25,'Use-Case Portfolio'!$V$6:$V$45,0)) -> Now (0-12m)
A26: 5 | B26: =INDEX('Use-Case Portfolio'!$A$6:$A$45,MATCH(A26,'Use-Case Portfolio'!$V$6:$V$45,0)) -> E-03 | C26: =INDEX('Use-Case Portfolio'!$E$6:$E$45,MATCH(A26,'Use-Case Portfolio'!$V$6:$V$45,0)) -> Payment repair & STP uplift | D26: =INDEX('Use-Case Portfolio'!$B$6:$B$45,MATCH(A26,'Use-Case Portfolio'!$V$6:$V$45,0)) -> Efficiency | E26: =INDEX('Use-Case Portfolio'!$P$6:$P$45,MATCH(A26,'Use-Case Portfolio'!$V$6:$V$45,0)) -> 87 | F26: =INDEX('Use-Case Portfolio'!$Q$6:$Q$45,MATCH(A26,'Use-Case Portfolio'!$V$6:$V$45,0)) -> Now (0-12m)
A27: 6 | B27: =INDEX('Use-Case Portfolio'!$A$6:$A$45,MATCH(A27,'Use-Case Portfolio'!$V$6:$V$45,0)) -> P-01 | C27: =INDEX('Use-Case Portfolio'!$E$6:$E$45,MATCH(A27,'Use-Case Portfolio'!$V$6:$V$45,0)) -> Fee leakage & billing accuracy engine | D27: =INDEX('Use-Case Portfolio'!$B$6:$B$45,MATCH(A27,'Use-Case Portfolio'!$V$6:$V$45,0)) -> Pricing | E27: =INDEX('Use-Case Portfolio'!$P$6:$P$45,MATCH(A27,'Use-Case Portfolio'!$V$6:$V$45,0)) -> 87 | F27: =INDEX('Use-Case Portfolio'!$Q$6:$Q$45,MATCH(A27,'Use-Case Portfolio'!$V$6:$V$45,0)) -> Now (0-12m)
A28: 7 | B28: =INDEX('Use-Case Portfolio'!$A$6:$A$45,MATCH(A28,'Use-Case Portfolio'!$V$6:$V$45,0)) -> C-01 | C28: =INDEX('Use-Case Portfolio'!$E$6:$E$45,MATCH(A28,'Use-Case Portfolio'!$V$6:$V$45,0)) -> Cash-flow forecasting for treasurers (in CitiDirect) | D28: =INDEX('Use-Case Portfolio'!$B$6:$B$45,MATCH(A28,'Use-Case Portfolio'!$V$6:$V$45,0)) -> Client | E28: =INDEX('Use-Case Portfolio'!$P$6:$P$45,MATCH(A28,'Use-Case Portfolio'!$V$6:$V$45,0)) -> 87 | F28: =INDEX('Use-Case Portfolio'!$Q$6:$Q$45,MATCH(A28,'Use-Case Portfolio'!$V$6:$V$45,0)) -> Now (0-12m)
A29: 8 | B29: =INDEX('Use-Case Portfolio'!$A$6:$A$45,MATCH(A29,'Use-Case Portfolio'!$V$6:$V$45,0)) -> C-05 | C29: =INDEX('Use-Case Portfolio'!$E$6:$E$45,MATCH(A29,'Use-Case Portfolio'!$V$6:$V$45,0)) -> CitiDirect AI assistant — scale to 30 markets | D29: =INDEX('Use-Case Portfolio'!$B$6:$B$45,MATCH(A29,'Use-Case Portfolio'!$V$6:$V$45,0)) -> Client | E29: =INDEX('Use-Case Portfolio'!$P$6:$P$45,MATCH(A29,'Use-Case Portfolio'!$V$6:$V$45,0)) -> 85 | F29: =INDEX('Use-Case Portfolio'!$Q$6:$Q$45,MATCH(A29,'Use-Case Portfolio'!$V$6:$V$45,0)) -> Now (0-12m)
A30: 9 | B30: =INDEX('Use-Case Portfolio'!$A$6:$A$45,MATCH(A30,'Use-Case Portfolio'!$V$6:$V$45,0)) -> I-06 | C30: =INDEX('Use-Case Portfolio'!$E$6:$E$45,MATCH(A30,'Use-Case Portfolio'!$V$6:$V$45,0)) -> Tech Assist — developer agents on Services platforms | D30: =INDEX('Use-Case Portfolio'!$B$6:$B$45,MATCH(A30,'Use-Case Portfolio'!$V$6:$V$45,0)) -> Internal | E30: =INDEX('Use-Case Portfolio'!$P$6:$P$45,MATCH(A30,'Use-Case Portfolio'!$V$6:$V$45,0)) -> 84 | F30: =INDEX('Use-Case Portfolio'!$Q$6:$Q$45,MATCH(A30,'Use-Case Portfolio'!$V$6:$V$45,0)) -> Now (0-12m)
A31: 10 | B31: =INDEX('Use-Case Portfolio'!$A$6:$A$45,MATCH(A31,'Use-Case Portfolio'!$V$6:$V$45,0)) -> E-07 | C31: =INDEX('Use-Case Portfolio'!$E$6:$E$45,MATCH(A31,'Use-Case Portfolio'!$V$6:$V$45,0)) -> Trade finance document checking | D31: =INDEX('Use-Case Portfolio'!$B$6:$B$45,MATCH(A31,'Use-Case Portfolio'!$V$6:$V$45,0)) -> Efficiency | E31: =INDEX('Use-Case Portfolio'!$P$6:$P$45,MATCH(A31,'Use-Case Portfolio'!$V$6:$V$45,0)) -> 81 | F31: =INDEX('Use-Case Portfolio'!$Q$6:$Q$45,MATCH(A31,'Use-Case Portfolio'!$V$6:$V$45,0)) -> Now (0-12m)
A32: 11 | B32: =INDEX('Use-Case Portfolio'!$A$6:$A$45,MATCH(A32,'Use-Case Portfolio'!$V$6:$V$45,0)) -> D-01 | C32: =INDEX('Use-Case Portfolio'!$E$6:$E$45,MATCH(A32,'Use-Case Portfolio'!$V$6:$V$45,0)) -> Discovery synthesis from inquiries & interviews | D32: =INDEX('Use-Case Portfolio'!$B$6:$B$45,MATCH(A32,'Use-Case Portfolio'!$V$6:$V$45,0)) -> Product | E32: =INDEX('Use-Case Portfolio'!$P$6:$P$45,MATCH(A32,'Use-Case Portfolio'!$V$6:$V$45,0)) -> 81 | F32: =INDEX('Use-Case Portfolio'!$Q$6:$Q$45,MATCH(A32,'Use-Case Portfolio'!$V$6:$V$45,0)) -> Now (0-12m)
A33: 12 | B33: =INDEX('Use-Case Portfolio'!$A$6:$A$45,MATCH(A33,'Use-Case Portfolio'!$V$6:$V$45,0)) -> P-06 | C33: =INDEX('Use-Case Portfolio'!$E$6:$E$45,MATCH(A33,'Use-Case Portfolio'!$V$6:$V$45,0)) -> Attrition & wallet-share early warning | D33: =INDEX('Use-Case Portfolio'!$B$6:$B$45,MATCH(A33,'Use-Case Portfolio'!$V$6:$V$45,0)) -> Pricing | E33: =INDEX('Use-Case Portfolio'!$P$6:$P$45,MATCH(A33,'Use-Case Portfolio'!$V$6:$V$45,0)) -> 80 | F33: =INDEX('Use-Case Portfolio'!$Q$6:$Q$45,MATCH(A33,'Use-Case Portfolio'!$V$6:$V$45,0)) -> Now (0-12m)

Sheet Systems View
A1: Systems View — the AI program as a system, not a list of projects
A2: Purpose of the system (Ackoff): convert Services' data exhaust and client relationships into governed, compounding decision capability that lowers cost-to-serve and raises client value within the bank's risk appetite. Read: stocks → loops → leverage points → binding constraint → archetypes to avoid → delays.
A4: A. Stocks and flows (what accumulates)
A5: Stock | B5: Inflows | C5: Outflows / leaks | D5: State today (assessed) | E5: Target signal
A6: Trusted, ontology-mapped data | B6: Lineage work, golden-source designation, ISO 20022 adoption | C6: Schema drift, market-specific exceptions, unowned datasets | D6: Low-medium: consent-order remediation still open; ontology not yet a product | E6: Readiness score ≥ 4 on the 8 priority entities
A7: Reusable AI components | B7: Component product owners, platform funding, pattern extraction from use cases | C7: Bespoke builds, vendor lock-in, unmaintained pilots | D7: Enterprise stack strong; Services-specific components thin | E7: ≥ 6 components with owners and SLAs (IDP, RAG, evals, guardrails, agent runtime, telemetry)
A8: Validated models/agents in inventory | B8: Pipeline throughput (validation capacity × pre-approved patterns) | C8: Retirement, drift failures, regulatory re-scoping | D8: 50+ use-case pipeline; production count undisclosed | E8: ≥ 25 in production with monitoring
A9: Control coverage | B9: Tiered control library, eval harness, monitoring | C9: New capability classes (agents) outpacing controls | D9: Traditional MRM mature; GenAI/agentic controls forming (SR 26-2 shifts onus to bank) | E9: 100% of Tier-3/4 use cases with evidence pack
A10: Client trust and co-creation relationships | B10: Design-partner cohorts, transparent explanations, reliability | C10: Incidents, opaque recommendations, over-automation | D10: CitiDirect assistant pilot; Sales Assist; few named client co-creation programs | E10: 10 design partners per business line; NPS on AI features tracked
A11: Workforce AI fluency | B11: Training (mandatory prompt training), accelerators, workflow redesign | C11: Attrition of AI leaders, tool fatigue | D11: 70–90% adoption; AI leadership churn in 2026 | E11: Roles redesigned; fluency in performance criteria
A12: Value realized (P&L) | B12: Use cases reaching scale with Finance-verified attribution | C12: Benefit leakage (hours saved not redeployed), double counting | D12: Activity metrics dominate; no $ disclosed | E12: Value ledger reconciled quarterly; AI-attributed revenue and cost published
A14: B. Feedback loops (R = reinforcing, B = balancing)
A15: Loop | B15: Mechanism | C15: Type | D15: Where it is today | E15: How to strengthen (R) / relieve (B) | F15: Signal it is working
A16: R1 Data flywheel | B16: More production use → more labeled outcomes (cases, repairs, forecasts) → better models → more use | C16: R | D16: Weak: pilots don't feed a shared corpus; labels not captured systematically | E16: Instrument every use case to write outcomes back to the entity model (Case, Forecast, Instruction) | F16: Every Now-wave use case ships with an outcome-capture spec
A17: R2 Reuse flywheel | B17: Components → faster delivery → more use cases → more patterns extracted → richer components | C17: R | D17: Forming at enterprise level; Services builds still bespoke | E17: Fund component owners; require 'compose, don't build' at intake | F17: ≥ 60% of new use cases composed from existing components by month 12
A18: R3 Client co-creation flywheel | B18: Design partners → adoption → references → RFP wins → more partners and data | C18: R | D18: Not yet running for AI products; strong for core products | E18: Cohorts per business line; publish anonymized outcomes; embed AI features in RFP content (I-01) | F18: Cohort size; reference-able clients; AI mentions in won RFPs
A19: R4 Sponsorship flywheel | B19: Verified value → executive sponsorship → budget and decision rights → more verified value | C19: R | D19: Blocked by measurement (activity metrics, no ledger) | E19: Value ledger with Finance; quarterly value report | F19: Budget for AI in Services tied to ledger, not to pilot count
A20: B1 Governance throughput | B20: More use cases → longer validation/control queue → slower delivery → fewer use cases (or shadow AI) | C20: B | D20: Likely active: 50+ pipeline vs finite MRM capacity; SR 26-2 removes GenAI from MRM scope, so Services must design its own gate | E20: Tiered regime; pre-approved patterns; joint MRM–Services pod; validation SLAs | F20: Median intake→production ≤ 90 days for Tier 1–2; ≤ 180 for Tier 3
A21: B2 Run-cost pressure | B21: Scale → inference/token cost → CFO pushback → throttled scaling (McKinsey 2026: 20% of firms constrained by token costs) | C21: B | D21: Emerging as agents scale | E21: Cost-per-run telemetry; model tiering (small models for routine); unit-cost targets per use case | F21: Cost per transaction/inquiry trending down as volume rises
A22: B3 Trust erosion | B22: One visible incident → tighter controls → slower delivery and lower adoption | C22: B | D22: Latent; consequences are severe in a consent-order environment | E22: Canary releases; kill switches; incident playbooks; over-communicate limits to clients | F22: Zero client-facing incidents; time-to-contain < 1 hour
A23: B4 Jurisdictional divergence | B23: More markets → more local rules and approvals → slower global releases | C23: B | D23: Structural (90+ countries; EU AI Act 2027, MAS, HKMA, Colorado 2027) | E23: Jurisdiction as first-class entity; localization agent (D-03); regional control mapping | F23: Markets per release rising while lead time falls
A25: C. Leverage points (Meadows — ordered from most to least powerful)
A26: Leverage point | B26: Intervention | C26: Why it is high-leverage | D26: Owner | E26: First artifact
A27: Paradigm | B27: From 'AI is a tool we roll out' to 'AI is a product line with a P&L and a pipeline' | C27: Changes what gets funded, measured and celebrated | D27: Head of Services + this role | E27: Investor-Day-style narrative for Services AI with value targets
A28: Goals | B28: Replace user/prompt counts with P&L, client adoption and cycle-time goals | C28: Redirects the whole system toward value realization | D28: Services CFO + AI product lead | E28: Value ledger live; goals in scorecards
A29: Rules | B29: Tiered control regime with pre-approved patterns; 'compose, don't build'; ontology readiness gate | C29: Makes the fast lane fast and the slow lane safe | D29: MRM + ORM + AI product lead | E29: Control library v1; intake checklist
A30: Information flows | B30: Shared ontology, outcome capture, cost-per-run telemetry, quarterly value report | C30: Lets every loop above see itself | D30: Platforms & Data Solutions | E30: Ontology v1; telemetry standard
A31: Feedback-loop gain | B31: Client co-creation cadence (monthly), incident learning loop | C31: Strengthens R3, dampens B3 | D31: Business-line product heads | E31: Cohorts running; retros published
A32: Delays | B32: Validation SLA; data onboarding SLA; regional approval calendar | C32: Shortening delays is the cheapest throughput gain | D32: MRM + regional COOs | E32: Median cycle times tracked and falling
A33: Buffers | B33: Platform capacity reserve; evaluation datasets; sandbox environments per market | C33: Prevents the shared platform becoming the bottleneck | D33: Services Technology | E33: Capacity plan with headroom
A34: Structure | B34: Hub-and-spoke with business-line AI product leads owning P&L | C34: Aligns accountability with value | D34: Group Head of AI + Services | E34: RACI adopted
A36: D. Binding constraint (Goldratt — five focusing steps)
A37: Step | B37: Applied to Services
A38: 1. Identify | B38: The governed path to production: data readiness + tiered validation/control design + reusable components. Not model capability, not budget, not talent (enterprise already supplies these).
A39: 2. Exploit | B39: Pre-approved patterns for Tier 1–2 (retrieve/generate/extract) so 60–70% of the pipeline never waits; joint MRM–Services pod for Tier 3–4; ontology readiness gate so nothing enters the constraint unprepared.
A40: 3. Subordinate | B40: Intake volume matched to constraint capacity; business lines get a quota of Tier-3/4 slots per quarter; roadmap sequenced by readiness, not enthusiasm.
A41: 4. Elevate | B41: Invest in validation capacity (people + eval harness automation), lineage tooling, and component owners; measure cycle time as a first-class KPI.
A42: 5. Repeat | B42: When cycle time stops being the constraint, expect the next one to be client procurement/data-sharing (for client products) or run-cost (for agents) — pre-plan both.
A44: E. System archetypes to avoid (Senge)
A45: Archetype | B45: How it would show up here | C45: Structural countermeasure
A46: Fixes that fail — 'pilot theater' | B46: Pilots relieve pressure to show AI progress; production never arrives; pressure returns (MIT: 95% of GenAI pilots show no P&L impact) | C46: Every pilot has a production owner, a value hypothesis and a kill date
A47: Shifting the burden — vendor dependency | B47: Buying vendor agents relieves delivery pressure; internal capability atrophies; switching costs rise | C47: Abstraction layer; multi-model; component ownership stays internal
A48: Limits to growth — data quality | B48: Use-case growth stalls when data readiness is the limit; more model effort doesn't help | C48: Fund the ontology as a product before scaling use-case count
A49: Tragedy of the commons — shared platform | B49: Every business line pulls on enterprise platform capacity; nobody funds headroom | C49: Capacity reserve and chargeback; buffers (C above)
A50: Success to the successful — Payments takes all | B50: The biggest line wins every funding round; LMS/Trade/Securities AI starves although LMS has the NII lever | C50: Portfolio balance rule by mandate and business line (Portfolio Summary)
A52: F. Delays to plan for (assumptions — validate internally)
A53: Delay | B53: Typical duration | C53: Mitigation
A54: Model validation (Tier 3–4) | B54: 8–16 weeks | C54: Parallelize with build; start evidence pack at intake
A55: Data onboarding to a governed corpus | B55: 4–12 weeks per source | C55: Ontology readiness gate; prioritize 8 entities
A56: Client procurement / data-sharing for co-creation | B56: 3–9 months | C56: Standard design-partner agreement; start cohort recruitment in month 1
A57: Regional approvals for a new market | B57: 1–6 months | C57: Approval calendar; localization agent pre-fills evidence
A58: Benefit realization after go-live | B58: 1–2 quarters | C58: Finance attribution rules agreed before launch

Sheet Operating Model & Governance
A1: Operating Model & Governance — how this is done at a global bank (domain confirmation)
A2: What a Director-level AI product lead in Services actually operates: one pipeline, tiered controls, hub-and-spoke with the enterprise AI organization, and a regulatory map for 30+ markets. Durations are typical-practice assumptions; confirm Citi's actual SLAs.
A4: A. The use-case pipeline (intake → production → monitoring)
A5: Stage | B5: Who | C5: Artifact | D5: Typical duration (assumption) | E5: Exit criteria | F5: Practice note
A6: 1. Intake | B6: Business-line AI product lead | C6: One-page charter: problem, entities, capability, tier hypothesis, value hypothesis, owner | D6: 1–2 weeks | E6: Charter approved; ontology readiness ≥ 3 on required entities | F6: Everyone submits through the same door — internal and client use cases alike
A7: 2. Value & risk tiering | B7: AI product lead + MRM + ORM + Compliance | C7: Tier (1–4), value estimate, control checklist | D7: 1 week | E7: Tier agreed; pre-approved pattern identified (or not) | F7: Tier drives everything downstream; get it right early
A8: 3. Data & ontology readiness | B8: Platforms & Data Solutions | C8: Golden sources confirmed; entitlements; retention/residency check | D8: 2–8 weeks | E8: Readiness ≥ 4; lineage documented | F8: The step most banks skip and then pay for at validation
A9: 4. Build (compose from components) | B9: Delivery pod (product, engineering, data science, control partner) | C9: Working solution on shared components; eval set; guardrails | D9: 4–12 weeks | E9: Evals pass thresholds; cost per run within target | F9: Pod includes a control partner from day one (JD: 'partner with Legal, Risk, Compliance and Model Risk from day one')
A10: 5. Validation (tier-dependent) | B10: MRM (traditional models) / AI governance (GenAI, agents) | C10: Validation report or GenAI assurance pack: performance, robustness, bias, explainability, prompt/response tests, red-team | D10: Tier 1–2: 2–4 weeks; Tier 3–4: 8–16 weeks | E10: Sign-off; conditions of use | F10: SR 26-2 (Apr 2026) excludes GenAI/agentic from MRM scope → the bank's own AI governance must be at least as rigorous
A11: 6. Controls & regional approvals | B11: ORM, Compliance, Legal, Privacy, InfoSec, regional COOs | C11: Control design & testing evidence; DPIA where needed; market approvals | D11: 2–12 weeks (parallel) | E11: Controls tested; approvals for launch markets | F11: Global design, local controls — jurisdiction entity pre-fills evidence
A12: 7. Limited production (canary) | B12: Product lead + Ops | C12: Live with a bounded population; monitoring dashboards; kill switch tested | D12: 4–8 weeks | E12: KPIs on track; no incidents; user feedback loop running | F12: Design partners here for client products
A13: 8. Scale & monitor | B13: Product lead; model monitoring team | C13: Drift, performance, cost, incident metrics; periodic review; value ledger entry | D13: Ongoing | E13: Finance-verified value; annual re-validation for Tier 3–4 | F13: Benefit realization is a step, not an assumption
A15: B. Structure — hub and spoke (who does what)
A16: Unit | B16: Responsibilities | C16: Role in the system | D16: Citi-specific note
A17: Hub: Firmwide AI organization (Group Head of AI; Office of AI Strategy; platforms; standards) | B17: Model access and contracts (Gemini, Anthropic, Llama…), shared platform (Stylus Workspaces, agent runtime), enterprise standards, responsible-AI policy, training, vendor risk | C17: Sets the rules of the game; provides the picks and shovels | D17: Citi reorganized this in May 2026 (Group Head of AI; merged CTO/Head-of-AI responsibilities) — [verify current structure with the hiring manager]
A18: Spoke: Services AI product office (this role per business line) | B18: Business-line AI strategy, use-case pipeline, business cases and P&L, client co-creation, GTM, value ledger, adoption | C18: Owns outcomes for the business line | D18: The JD in one line: 'AI is the tool and measurable business outcomes are the mission'
A19: Services Platforms & Data Solutions | B19: Ontology/data products, lineage, telemetry, Services-specific components | C19: Owns the foundation the spokes build on | D19: Existing function (Head of Platforms & Data Solutions, Services) — natural partner
A20: Risk partners: MRM, ORM, Compliance (incl. sanctions/AML), Legal, Privacy, InfoSec | B20: Tiering, validation, control design, regulatory interpretation, third-party risk | C20: Second line; embedded in pods as control partners | D20: Services already posts AI Risk & Governance roles (e.g., Trade Finance SVP, Aug 2026) — leverage them
A21: Guilds: AI Champions / Accelerators (4,000 firmwide) | B21: Workflow redesign in teams, adoption, feedback | C21: Distribution channel for change | D21: Use for Internal-mandate use cases; measure redeployed hours
A22: Regional Services COOs / market heads | B22: Local rules, approvals, adoption in 90+ countries | C22: Veto and enabling power per market | D22: Bring into the approval calendar early; they decide launch order
A23: Finance (Services CFO) | B23: Attribution rules, value ledger sign-off, investment gating | C23: Makes value real | D23: Without Finance the ledger is a spreadsheet; with Finance it is a P&L
A25: C. Control tiers (what 'responsible AI' means operationally)
A26: Tier | B26: Definition | C26: Examples | D26: Minimum controls | E26: Review path | F26: Portfolio IDs
A27: Tier 1 — Assist | B27: Human reads and decides; internal; no client output | C27: Policy Q&A, summaries, drafts for internal use | D27: Logging, entitlement-aware retrieval, citation, acceptable-use, basic evals | E27: Pre-approved pattern; light review | F27: I-04, D-01, D-02
A28: Tier 2 — Recommend (internal) | B28: AI proposes; human approves before anything leaves the team | C28: RFP drafts, coverage briefs, repair suggestions | D28: Tier 1 + eval thresholds, red-team for prompt injection, output filters, human-in-loop evidence | E28: Pattern-based review; sample audits | F28: I-01, I-02, I-03, E-03, E-10
A29: Tier 3 — Recommend/Act bounded (client-affecting or money-adjacent) | B29: AI acts within allow-lists and limits, or recommends to clients; post-hoc review | C29: Pricing recommendations, liquidity structures, reconciliation actions, investigations outreach | D29: Tier 2 + explainability, conduct/fairness review, action allow-lists, spend/volume caps, kill switch, full trace, drift monitoring | E29: Formal validation/assurance; annual re-review | F29: P-02, C-02, C-03, E-04, E-05, C-01
A30: Tier 4 — Client decisioning / financial-crime / autonomous | B30: Model outcome affects client access, screening or executes payments | C30: Sanctions/AML triage, fraud decisions, agent-initiated payments | D30: Tier 3 + independent validation, bias testing, regulator-facing documentation, dual control, staged rollout, board-level reporting | E30: Full MRM-grade validation; regulatory engagement | F30: E-02, E-08, C-06, C-09
A32: D. RACI for one use case (template)
A33: Activity | B33: Services AI product lead | C33: MRM / AI governance | D33: Platforms & Data / Engineering | E33: Regional COO / Compliance | F33: Finance
A34: Charter & value hypothesis | B34: A/R | C34: C | D34: C | E34: C | F34: I
A35: Tiering | B35: R | C35: A | D35: C | E35: I | F35: I
A36: Data readiness & lineage | B36: C | C36: C | D36: A/R | E36: I | F36: I
A37: Build & evals | B37: A | C37: C | D37: R | E37: I | F37: I
A38: Validation / assurance | B38: C | C38: A/R | D38: C | E38: I | F38: I
A39: Controls & regional approvals | B39: R | C39: C | D39: C | E39: A | F39: I
A40: Launch decision | B40: A | C40: C | D40: I | E40: C | F40: C
A41: Value attribution | B41: R | C41: I | D41: I | E41: I | F41: A
A42: Monitoring & incident | B42: A | C42: C | D42: R | E42: C | F42: I
A44: E. Regulatory map for a 30+-market rollout (as of Sep 2026)
A45: Jurisdiction | B45: What is in force / coming | C45: Implication for Services AI | D45: Action
A46: United States (Fed/OCC/FDIC) | B46: Revised interagency Model Risk Management guidance (SR 26-2 / OCC 2026-13, 17 Apr 2026) replaces SR 11-7: principles-based, materiality tiers; generative and agentic AI explicitly out of scope; agencies plan an RFI on AI use. OCC and Fed leadership signal 'innovation-encouraging' posture. | C46: Traditional predictive models: MRM as before. GenAI/agents: Citi's own AI governance must document rigor — regulators will still examine it under safety-and-soundness. NIST AI RMF + GenAI profile as the reference frame. | D46: Design the Tier 3–4 assurance pack now; do not wait for an RFI outcome.
A47: US states | B47: Colorado ADMT Act (SB 26-189, signed May 2026, effective 1 Jan 2027): financial services in scope; pre-decision notice, adverse-outcome explanation, human review. NYDFS letters on AI cyber risk (Oct 2024) and frontier-model risk (May 2026). Federal push for preemption (EO Dec 2025). | C47: Client-decisioning use cases (credit-adjacent supplier scoring, screening outcomes) need notice/explanation/human-review paths. | D47: Explainability and human review are Tier-3/4 defaults anyway.
A48: European Union | B48: AI Act: Digital Omnibus (May 2026) defers Annex III high-risk obligations (incl. creditworthiness) to 2 Dec 2027; GPAI (Aug 2025) and Art. 50 transparency (Aug 2026) in force; AI literacy duty since Feb 2025. | C48: Transparency obligations apply now to client-facing assistants; high-risk classification matters for supplier credit scoring and any employment-related use. | D48: Map each Tier 3–4 use case to Annex III; keep technical documentation ready for 2027.
A49: United Kingdom | B49: Technology-neutral: Consumer Duty, SM&CR, PRA SS1/23 model risk; FCA AI Lab, Supercharged Sandbox, AI Live Testing; HM Treasury FS AI Adoption Plan (Jul 2026) flags agentic payments and 'Know Your Agent'. | C49: Accountability sits with named senior managers; agentic payments will need agent identity and liability clarity. | D49: Use FCA AI Live Testing for C-09 if UK is a launch market.
A50: Singapore (MAS) | B50: Guidelines on AI Risk Management consulted Nov 2025 (board oversight, AI inventory, materiality, lifecycle controls, third-party accountability; covers GenAI and agents); industry AI Risk Management Toolkit (Mar 2026). Final issuance [verify]. | C50: Expect AI inventory and materiality assessment requirements that mirror the tiering here. | D50: Singapore is a natural APAC launch market (Citi Services AI roles posted there).
A51: Hong Kong (HKMA) | B51: GenAI consumer-protection circular (Aug 2024); GenA.I. Sandbox cohorts and cross-sector Sandbox++ (Mar 2026); Mar 2026 circular requiring board-endorsed digital/AI strategies (incl. agentic) by 9 Sep 2026. | C51: Board-level strategy documentation for HK entity; sandbox route for client pilots.
A52: Cross-border payments / agentic | B52: EPAA–HSBC working group on AI agent payment liability (Jul 2026); Swift AI fraud service and federated-learning pilots; IMF note (Apr 2026) on probabilistic AI vs deterministic payment rails. | C52: Standards for agent identity/authorization/liability are forming now — participation is cheap, absence is costly. | D52: Join the standards bodies; pilot C-09 with 5 clients under explicit mandates.
A54: F. Model and vendor strategy (what the hub gives you, what the spoke decides)
A55: Decision | B55: Position | C55: Decision right
A56: Multi-model by design | B56: Citi runs Gemini (primary), Anthropic Claude and Llama; CTO stated preference for closed-source models. Keep an abstraction layer so use cases are model-portable. | C56: Spoke decides model per use case within the hub's approved list; hub negotiates contracts.
A57: Build vs buy vs partner | B57: Buy platforms and components (IDP, agent runtimes); build the ontology, evals, and domain workflows; partner with networks (Swift, Mastercard, Visa) on agentic rails and fraud signals. MIT NANDA: vendor partnerships ~2x success of internal builds for generic capability — but domain workflows are the moat. | C57: Spoke owns the 'what'; hub owns the 'with what'.
A58: Cost governance | B58: Cost-per-run telemetry from day one; small models for routine classification; caching; unit-cost targets per use case. | C58: Spoke owns unit-cost targets; hub owns rate cards.
A59: Third-party and concentration risk | B59: Google Cloud is a strategic dependency (risk models, HPC, apps); document exit options; NYDFS third-party expectations. | C59: Hub; spoke documents dependency per use case.

Sheet Pricing & Commercial
A1: Pricing & Commercial — AI for pricing, and pricing of AI
A2: Two different questions. (1) How AI improves Services' own pricing and yield. (2) How AI-enabled client features are monetized. The economics of transaction banking decide both: FY2025 NII $12.2B vs fee revenue $3.1B — roughly 80% of revenue is balance-driven, so the biggest commercial lever of client AI is operating balances and share of wallet, not feature fees.
A4: A. Where Services makes money, and how AI touches each lever
A5: Revenue / cost lever | B5: Mechanism | C5: AI use cases that move it | D5: Order of magnitude (illustrative) | E5: Commercial priority
A6: Operating deposits / NII (~$12.2B FY25; >$1T average deposits) | B6: Balances follow operational flows and structure quality; deposit beta sets margin | C6: Forecasting and liquidity optimization that keep more operating cash with Citi (C-01, C-02); deposit pricing intelligence (P-03) | D6: 25 bps of incremental average deposits ≈ $2.5B balances ≈ $30M NII at a 1.2% spread (illustrative — see Business Case) | E6: Highest
A7: Payment and clearing fees, FX margin | B7: Volume × yield; yield erodes with competition and mis-pricing | C7: Leakage engine (P-01), FX/fee yield optimization (P-05), routing that captures FX (C-03) | D7: 1% leakage recovery on $3.1B fees ≈ $31M (illustrative) | E7: High
A8: Trade and working-capital financing | B8: Financing margin × utilization; onboarding speed drives utilization | C8: Supplier onboarding and risk scoring (C-08), receivables (C-04), trade docs (C-07/E-07) | D8: Time-to-first-draw and utilization | E8: High
A9: Securities services fees | B9: AUC/A-based and activity fees; cost-to-serve | C9: Custody+ intelligence (C-10), reconciliations (E-05), corporate actions (E-06) | D9: Cost per transaction (Citi cites −25%) | E9: Medium–high
A10: Cost-to-serve | B10: Servicing, onboarding, exceptions, screening labor | C10: Agent Assist (E-10), IDP (E-01), repair (E-03), triage (E-02) | D10: 20–25% servicing effort reduction cited by Citi | E10: High
A11: Retention and share of wallet | B11: ~75% of Services revenue is from clients also using Markets/Banking; attrition is expensive | C11: Attrition early warning (P-06), coverage briefing (I-02), AI features embedded in RFPs (I-01) | D11: Revenue retained; win rate | E11: High
A13: B. AI for pricing — use cases and guardrails
A14: Use case | B14: Mechanism | C14: Entities | D14: Horizon | E14: Guardrails | F14: KPI
A15: P-01 Fee leakage & billing accuracy | B15: Contract terms (IDP on pricing agreements) vs fees applied per transaction; waivers and mis-tiers flagged | C15: Fee schedule, Transaction, Relationship | D15: Now | E15: Recovery must respect contractual commitments; client communication scripted | F15: Leakage recovered; billing accuracy
A16: P-02 Relationship pricing optimization | B16: Price bands by wallet, elasticity, bundle, cost-to-serve; explanation for deal desk | C16: Relationship, Fee schedule, Product | D16: Next | E16: Antitrust/conduct review; no coordination signals; documented human override; fairness across similar clients | F16: Price yield; discount variance
A17: P-03 Deposit pricing & beta intelligence | B17: Operating vs non-operating classification; segment-level rate sensitivity; policy-bounded recommendations | C17: Account, Relationship, Forecast | D17: Next | E17: Treasury/ALM policy limits; model validation (traditional MRM in scope) | F17: Beta forecast error; balance retention
A18: P-04 RFP price-to-win | B18: Learns from win/loss to recommend price points | C18: Relationship, Fee schedule | D18: Now | E18: Avoid race-to-bottom; margin floors | F18: Win rate at target price
A19: P-05 FX margin & fee yield | B19: Yield optimization within disclosure rules; erosion detection | C19: Transaction, Fee schedule, Jurisdiction | D19: Next | E19: Conduct rules on FX margins; disclosure; complaints monitoring | F19: FX and fee yield
A20: P-06 Attrition early warning | B20: Declining flows/balances → propensity → coverage action | C20: Relationship, Account, Instruction | D20: Now | E20: None beyond data use policy | F20: Saves; revenue retained
A22: C. Pricing of AI — monetization models for client-facing features
A23: Model | B23: How it works | C23: Peer example | D23: Risk | E23: Recommendation for Services
A24: Bundled / defensive | B24: Feature included in the core relationship to defend share, NPS and RFP position | C24: BofA CashPro Forecasting (3,000+ clients, no separate fee reported); JPM cash-flow forecasting in Payments | D24: Undervalues the feature; hard to un-bundle later | E24: Default for assistants, basic forecasting, anomaly alerts, document pre-checks — trust features are never sold
A25: Tiered premium | B25: Advanced analytics/optimization in a paid tier (e.g., multi-entity liquidity optimization, scenario simulation) | C25: Treasury-tech (Kyriba, HighRadius) charge for forecasting/optimization modules | D25: Clients compare to TMS vendors; requires clear incremental value | E25: Use for C-02 liquidity optimization and D-05 data products; test in Commercial segment first
A26: Usage-based | B26: Per API call, per agent action, per document processed | C26: Stripe/Adyen per-transaction; cloud-style metering | D26: Discourages adoption early; billing complexity | E26: Use for C-09 agent rails and high-volume IDP (C-07) once adoption is proven
A27: Outcome / value-share | B27: Fee tied to measurable outcome (DSO days, working capital unlocked, leakage recovered for the client) | C27: Working-capital fintechs (Taulia, HighRadius) sell on outcomes | D27: Attribution disputes; needs baselines | E27: Use for C-04 receivables and SCF programs where outcome is auditable
A28: Balance-linked | B28: Premium features free above operating-balance thresholds | C28: Common in transaction-banking relationship pricing | D28: Must be transparent and consistent | E28: Best fit for Services economics: monetize via balances; formalize it
A29: Data / insight products | B29: Subscriptions for anonymized benchmarks and flow analytics | C29: JPM/BofA treasury insights | D29: Privacy, competition-law review, client trust | E29: Later horizon (D-05); pilot with design partners
A31: D. Commercial playbook (co-creation → pricing tests → GTM waves)
A32: Step | B32: What | C32: When | D32: Exit criteria
A33: 1. Design-partner cohort | B33: 10 clients per business line across segments and regions under a standard agreement (data use, feedback cadence, early access, no exclusivity) | C33: Month 1–3 | D33: Cohort signed; monthly cadence running
A34: 2. Pricing experiments | B34: Test bundled vs tiered vs balance-linked in the Commercial segment (fastest-growing, least contractual friction) | C34: Month 4–9 | D34: Willingness-to-pay curves; chosen model per feature
A35: 3. RFP embedding | B35: AI features written into standard RFP content (I-01); references from cohort | C35: Month 3 onward | D35: AI features cited in won RFPs
A36: 4. GTM in waves | B36: Wave 1: 5 markets, Commercial + large corporates; Wave 2: 15 markets incl. FI; Wave 3: 30+ markets | C36: Months 9–24 | D36: Markets live; active clients; NPS
A37: 5. Sales enablement | B37: Coverage briefing (I-02) and playbooks; incentives aligned to AI-feature adoption and balances, not feature revenue | C37: Month 6 onward | D37: Adoption per coverage team

Sheet Business Case
A1: Business Case — illustrative value model (edit blue cells)
A2: All inputs are public figures or labeled assumptions; the point is the structure — replace with Services baselines before showing it. Low/Base/High are multipliers on the Base lever value. Values in $ millions unless noted.
A4: A. Baseline inputs (public, FY2025 / Q2 2026)
A5: Input | B5: Value | C5: Unit | D5: Source / note
A6: Services revenue | B6: 21300 | C6: $M | D6: Citi FY2025 results (press release, Jan 2026): $21.3B (+8%)
A7: Services net interest income | B7: 12200 | C7: $M | D7: FY2025: $12.2B (+12%)
A8: Services non-interest (fee) revenue | B8: 3100 | C8: $M | D8: FY2025: $3.1B reported
A9: Services operating expenses | B9: 10800 | C9: $M | D9: FY2025: $10.8B (+2%)
A10: Average deposits | B10: 1017000 | C10: $M | D10: Q2 2026: $1.017T (+19%)
A11: Client service agents in scope | B11: 6000 | C11: agents | D11: Investor Day 2026 target; 1,200 live per Apr 2026 report [verify]
A12: Fully loaded cost per agent | B12: 0.075 | C12: $M/yr | D12: Assumption — replace with internal figure
A13: Inquiries handled per year | B13: 3000000 | C13: inquiries | D13: Investor Day 2026: 3M+
A14: Services platform/technology spend | B14: 2000 | C14: $M/yr | D14: Khaliq, UBS conference Feb 2026: 'north of $2B annually'
A15: Share of platform spend that is labor | B15: 0.6 | C15: % | D15: Assumption
A16: New client onboardings per year | B16: 5000 | C16: clients | D16: Assumption — replace with implementations data
A17: First-year revenue per onboarded client | B17: 0.2 | C17: $M | D17: Assumption
A18: Exceptions/investigations/screening ops cost base | B18: 400 | C18: $M/yr | D18: Assumption — replace with Ops cost allocation
A20: B. Value levers — assumptions (blue) and annual run-rate value (formulas)
A21: Lever | B21: Assumption | C21: Unit | D21: Base value ($M/yr) | E21: Mechanism / source
A22: 1. Servicing effort reduction (E-10, C-05, I-03) | B22: 0.2 | C22: % of agent effort | D22: =$B$11*$B$12*B22 -> 90 | E22: Citi cites 20–25% servicing effort reduction on 3M+ inquiries (Investor Day 2026). Value = agents × cost × reduction. Assumes redeployment/attrition capture.
A23: 2. Developer productivity on Services platforms (I-06, E-11) | B23: 0.15 | C23: % of labor spend | D23: =$B$14*$B$15*B23 -> 180 | E23: GitHub Copilot 5–15% (Citi), Devin 2–20x on specific tasks, Services cites 30–40% — 15% base is conservative. Value = platform spend × labor share × uplift (capacity, not cash, unless spend is reduced).
A24: 3. Onboarding cycle-time reduction (E-01, I-05) | B24: 20 | C24: days faster | D24: =$B$16*$B$17*B24/365 -> 54.794521 | E24: IDP cut doc review ~80% (hours → 10–15 min). Value = clients × first-year revenue × (days saved / 365) as revenue pull-forward; one-time uplift that recurs with volume.
A25: 4. Fee leakage recovery (P-01) | B25: 0.01 | C25: % of fee revenue | D25: =$B$8*B25*0.5 -> 15.5 | E25: Industry estimates of 1–3% leakage in transaction banking [verify]; 50% capture assumed (×0.5 hardcoded — edit in formula if needed).
A26: 5. Incremental operating deposits (C-01, C-02, P-03) | B26: 0.0025 | C26: % of avg deposits | D26: =$B$10*B26*B27 -> 30.51 | E26: 25 bps of average deposits retained/attracted via forecasting and liquidity optimization; NII at the spread below.
A27: Deposit spread assumption | B27: 0.012 | C27: % NII spread | E27: Assumption — Services NII/deposits ≈ 1.2% (12.2/1,017); replace with treasury transfer-pricing view.
A28: 6. Exceptions, investigations and screening efficiency (E-02, E-03, E-04, E-05) | B28: 0.25 | C28: % of ops cost base | D28: =$B$18*B28 -> 100 | E28: JPM: manual exceptions −50%, screening 2x volume with half the checks. 25% of an assumed $400M cost base.
A29: 7. Attrition avoided (P-06, I-02) | B29: 0.002 | C29: % of revenue | D29: =$B$6*B29 -> 42.6 | E29: 0.2% of revenue retained through early-warning and coverage actions. Assumption.
A30: Total annual run-rate value (Base) | D30: =SUM(D22,D23,D24,D25,D26,D28,D29) -> 513.40452
A31: …as % of Services operating expenses | D31: =D30/$B$9 -> 0.047537456
A32: …as % of Services revenue | D32: =D30/$B$6 -> 0.024103499
A34: C. Sensitivity (multipliers on Base) and investment / payback
A35: Scenario | B35: Multiplier | C35: Annual value ($M) | D35: Incremental investment ($M/yr) | E35: Net ($M/yr) | F35: Read
A36: Low | B36: 0.5 | C36: =$D$30*B36 -> 256.70226 | D36: 150 | E36: =C36-D36 -> 106.70226 | F36: Pilots stall; only servicing and dev productivity land
A37: Base | B37: 1 | C37: =$D$30*B37 -> 513.40452 | D37: 150 | E37: =C37-D37 -> 363.40452 | F37: Now-wave delivered; two client products GA
A38: High | B38: 1.5 | C38: =$D$30*B38 -> 770.10678 | D38: 150 | E38: =C38-D38 -> 620.10678 | F38: Pricing and deposit levers land; agentic rails add fees
A39: Investment of $150M/yr is an assumption: a Services-level AI product office, component funding and validation capacity on top of the enterprise platform (which Services already funds within its >$2B platform spend). Value figures are run-rate at scale (typically year 2–3), not year-1 cash. JPM's benchmark: ~$2B benefit on ~$2B AI spend firmwide (Dimon, Oct 2025). Treat this as the structure of the argument, not the number.

Sheet Roadmap
A1: Roadmap — nine workstreams × five periods
A2: Sequenced by the binding constraint: foundation and pipeline first, then the Now-wave use cases, then client products and pricing intelligence, then agentic and data-product bets. Each cell is a milestone; exit criteria are in the last row of each workstream.
A4: Workstream | B4: Days 0–90 | C4: Days 90–180 | D4: Months 6–12 | E4: Months 12–24 | F4: Months 24–36
A5: 1. Strategy & value governance | B5: Services AI product office chartered; decision rights and RACI agreed; value-ledger design with Finance; portfolio scored with business lines (this workbook as the workshop) | C5: First quarterly value report; portfolio re-scored; investment case approved | D5: Value ledger reconciled by Finance; AI goals in Services scorecards | E5: AI-attributed value reported in Services results; targets set through 2028 | F5: Services AI narrative external (Investor Day / Evident disclosure)
A6: 2. Ontology & data foundation | B6: Ontology v0: 8 priority entities, golden sources, readiness scores; merge with lineage program | C6: Ontology v1 in the data catalog; readiness gate live at intake; outcome-capture standard | D6: Jurisdiction entity encoded for 10 launch markets; Fee schedule digitized for top-500 relationships | E6: Ontology covers all 16 entities; 30 markets encoded; Forecast entity shared by C-01/C-02/P-03 | F6: Real-time, entitlement-aware access; ontology as a product with SLAs
A7: 3. Delivery pipeline & controls | B7: Tiering model and control library v1 agreed with MRM/ORM/Compliance; pre-approved Tier 1–2 patterns; validation SLAs proposed | C7: Joint MRM–Services pod running; eval harness shared; first Tier-3 assurance pack completed | D7: Median intake→production ≤ 90 days (Tier 1–2), ≤ 180 (Tier 3); regional approval calendar | E7: Tier-4 use cases (E-02, C-06) validated; agent controls (allow-lists, kill switch) standard | F7: Automated evidence generation; regulator engagement on agentic (EU AI Act 2027, MAS, HKMA)
A8: 4. Platform & reusable components | B8: Inventory enterprise components (IDP, RAG, evals, Stylus Workspaces, agent runtime); name Services component owners | C8: Cost-per-run telemetry live; IDP and RAG components with SLAs; model abstraction layer | D8: ≥ 6 components with owners; 60% of new use cases composed, not built | E8: Agent runtime hardened for Tier 3–4; small-model tiering for cost | F8: Composable platform; run-cost per transaction falling with volume
A9: 5. Use cases — waves | B9: Now wave in flight: E-01 (all markets), E-10, I-01, I-03, C-05, P-01, E-03, C-01 discovery | C9: First Now-wave use cases at scale with value attribution; E-04/E-05/E-06 started | D9: ≥ 5 use cases with Finance-verified value; C-01 canary with design partners; P-06, P-04 live | E9: Next wave in production: C-02, C-03, C-04, C-07, C-08, C-10, P-02, P-03, D-03, E-02, E-06; C-01 at scale | F9: Later wave: C-09 agentic rails, D-05 data products, E-09 reg reporting, I-07 reg-change intelligence, C-11, D-04
A10: 6. Client co-creation | B10: Design-partner agreement template; recruit first 10 clients (Payments/LMS) across regions | C10: Monthly cadence; CitiDirect assistant feedback loop; discovery synthesis (D-01) running | D10: Cohorts for Trade and Investor Services; reference-able outcomes published (anonymized) | E10: AI features in standard RFP content; NPS on AI features tracked; 30+ design partners | F10: Clients building on Citi agent rails; client advisory board on AI
A11: 7. Pricing & commercialization | B11: Fee leakage discovery (P-01) on top-500 relationships; pricing model options paper | C11: Leakage recovery running; pricing experiments designed for Commercial segment | D11: Bundled vs tiered vs balance-linked decisions per feature; Wave-1 GTM (5 markets) | E11: Pricing recommendations in ≥ 50% of deal-desk decisions; Wave-2 GTM (15 markets) | F11: Wave-3 GTM (30+ markets); value-share and usage models for receivables and agent rails
A12: 8. Talent & change | B12: Map roles touched by Now wave; AI Champions assigned per use case; skills baseline | C12: Workflow redesign for servicing and onboarding teams (not just tool access) | D12: Roles redefined for 3 workflows; fluency in performance criteria for AI product team | E12: Super-IC roles in product and ops; redeployment tracked against ledger | F12: AI-native org design for Services product and operations
A13: 9. Measurement & communication | B13: KPI tree per mandate (Strategy on a Page); telemetry standard; comms plan | C13: Quarterly value report #1 to Head of Services; pipeline dashboard | D13: Leading/lagging indicators in Services MBR; incident and learning loop reported | E13: External disclosure prepared (Transparency pillar); benchmark vs Evident peers | F13: Services recognized as transaction-banking AI leader
A15: Exit criteria by period (what 'done' means)
A16: Period | B16: Exit criteria
A17: Days 0–90 | B17: Office chartered; portfolio scored with owners; ontology v0; control library v1 agreed; 10 design partners in recruitment; Now wave started
A18: Days 90–180 | B18: First value report; pipeline SLAs live; components with owners; cohort cadence running; leakage recovery producing cash
A19: Months 6–12 | B19: ≥ 5 use cases with Finance-verified value; 2 client products in canary; cycle time targets met; Wave-1 GTM
A20: Months 12–24 | B20: ≥ 2 client products GA in 10+ markets with ≥ 500 active clients; pricing intelligence in deal desk; Tier-4 use cases validated; maturity ≥ 3.3
A21: Months 24–36 | B21: Agentic rails live with design partners; AI-attributed revenue disclosed; maturity ≥ 4.0; Evident contribution visible

Sheet Benchmarks & Peers
A1: Benchmarks & Peers — what others have done (2025–2026), and what Services should copy, adapt or avoid
A2: Dated facts; sources on the Sources tab. 'Copy' = proven and transferable; 'Adapt' = right idea, different economics; 'Avoid' = trap.
A4: A. Banks
A5: Bank | B5: What they did (dated) | C5: Transaction-banking relevance | D5: Implication for Services | E5: Verdict | F5: Note
A6: JPMorganChase (Evident #1) | B6: LLM Suite to ~200k+ staff (150k weekly users); AI 'paid for itself' — ~$2B benefit on ~$2B spend (Dimon, Oct 2025); 2026 tech budget $19.8B. Payments: manual exceptions −50% while volumes +50%; screening 2x volume with half the manual checks; KYC unit cost −40%; priorities: agentic commerce, cash-flow forecasting, sales enablement, pricing optimization; Kinexys tokenized settlement. | C6: Discloses $ value; business-line ownership; exceptions/screening as the efficiency engine | D6: Value ledger and disclosure; exceptions and screening first; pricing optimization as an explicit bet | E6: Copy | F6: JPM Payments line (Jun 2026): winners will have the most governable AI, not the most AI — the governance-as-product thesis in this workbook
A7: BNY | B7: Eliza platform: 125+ AI solutions in production; 134 'digital employees' with logins and personas; ~$3.8B tech spend (19% of revenue); OpenAI partnership; near-universal 10-hour training. | C7: Agents as first-class org members with identity and entitlements | D7: Agent identity/entitlement model for Tier-3 agents (E-04, E-05) | E7: Adapt | F7: Digital-employee framing works internally; client-facing needs stronger explainability
A8: Goldman Sachs | B8: GS AI Assistant firmwide (Jun 2025); Devin; six-month Anthropic collaboration on trade accounting/reconciliation and client-onboarding agents; OneGS 3.0 operating-model overhaul (Oct 2025). | C8: Agents on reconciliation and onboarding — direct analogs for Investor Services and Implementations | D8: E-05, I-05 patterns | E8: Copy | F8: Operating-model overhaul paired with AI — not AI alone
A9: Bank of America | B9: $13B tech spend; Erica 3.2B interactions; Erica for Employees ~90% of staff; CashPro Forecasting used by 3,000+ companies, 250k client hours saved, model 5x faster; Ask GPS internal GenAI; 18k developers with coding assistants; 15 GenAI use cases live from 45+ POCs. | C9: The closest peer for client-facing treasury AI: forecasting bundled into CashPro at scale | D9: C-01 as the first client product; bundled pricing; measure client hours saved | E9: Copy | F9: Note the funnel discipline: 45+ POCs → 15 live
A10: HSBC | B10: Chief AI Officer (Mar 2026); Global AI CoE Singapore (100+ hires); Google Cloud partnership targeting 200+ use cases; Mistral self-hosted; Mastercard B2B agentic-commerce pilot (May 2026); founding member of EPAA agent-payment liability working group; agentic trade-finance PoC with Microsoft/ANZ/Lloyds (LC parsing, ERP cross-check, sanctions/dual-use flags). | C10: Trade-finance agents and agentic-payment standards participation | D10: E-07/C-07 pattern; join standards bodies for C-09 | E10: Copy | F10: Singapore as APAC AI hub mirrors Citi's own Services AI postings there
A11: Wells Fargo | B11: Google Agentspace/Gemini toward 215k employees; Fargo 1B interactions; use cases incl. CIB FX post-trade inquiries, 250k vendor contracts/yr, KYC. | C11: Post-trade inquiry automation in CIB | D11: I-03 analog | E11: Adapt
A12: Standard Chartered | B12: SC GPT to 80k staff/~50 markets; 15,300 daily active users; 300+ use cases (30+ GenAI in production); ~6% average productivity uplift; 'AI Factory' of reusable components incl. agentic and IDP; transaction banking used it for legal-document analysis. | C12: Reusable-component factory in a multi-market transaction bank | D12: Component ownership model (R2 loop) | E12: Copy | F12: 6% average uplift is the honest number for broad assistants — the P&L comes from workflow redesign
A13: DBS | B13: S$1B AI economic value in 2025 (target set 2022); agentic credit-memo agents (70+ tasks) to ~1,500 corporate bankers targeting ≥30% time reduction (Aug 2026). | C13: Multi-year value target set publicly, then hit | D13: Set a Services value target with a date | E13: Copy
A14: Deutsche Bank | B14: Design partner for Google Cloud Gemini Enterprise for Financial Services (Aug 2026); first deployed in Corporate Bank MidCorp coverage; DB Lumina research tool. | C14: Coverage-side agent in a corporate bank (mid-market) | D14: I-02 for Commercial segment | E14: Adapt | F14: Citi Wealth is also a named design partner — Services can piggyback
A15: Citi (firmwide, for reference) | B15: Citi Assist/Stylus/Stylus Workspaces to 180k+ employees in 85 countries; ~9 in 10 using tools (Q2'26); Copilot + Devin to 40k developers (~100k hours/week); 100+ end-to-end processes mapped for automation; Citi Sky (Wealth, Apr 2026); Group Head of AI appointed May 2026 after Head of AI departure; Evident #12 (from #8). | C15: Enterprise foundation is strong; business-line value capture and disclosure lag | D15: Services can be the business line that closes the disclosure gap | E15: — | F15: Consent orders: OCC 2024 amendment terminated Dec 2025; 2020 orders remain; data/regulatory reporting is the residual
A17: B. Fintechs, networks and infrastructure (competitive and partnership context)
A18: Player | B18: What they did (dated) | C18: Relevance | D18: Implication | E18: Verdict
A19: Stripe | B19: Agentic Commerce Suite; Machine Payments Protocol (stablecoin/fiat agent payments); agent-ready financial accounts (pay invoices, create cards); conceded agentic commerce 'overhyped too early' (Feb 2026); OpenAI Instant Checkout discontinued Mar 2026. | C19: Threat at the Commercial/mid-market low end; agent payments still early | D19: Watch; do not over-invest in consumer-style agentic checkout | E19: Adapt
A20: Adyen | B20: 'Adyen Agentic' catalog/checkout/risk layer for AI agents; in Mastercard Agent Pay for Machines. | C20: Same as Stripe for merchants | D20: Watch | E20: Adapt
A21: Kyriba / HighRadius / SAP Taulia | B21: Kyriba TAI agentic (human-in-loop); HighRadius 186 agents across 20 products, 'fully autonomous by 2027'; SAP Taulia Working Capital Agent (GA Q4 2026, $1.2T volumes). | C21: TMS/AR vendors are moving into forecasting, receivables and working-capital decisions — the same space as C-01/C-02/C-04 | D21: Partner where they own the client's ERP workflow; compete on bank-side data (balances, flows) and execution | E21: Adapt
A22: Mastercard / Visa | B22: Agent Pay (Citi cardholders first, Oct–Nov 2025); Agent Pay for Machines (Jun 2026, 30+ partners); Visa Intelligent Commerce live with 30+ European issuers (Jul 2026); Trusted Agent Protocol. | C22: Networks are setting agent identity/authorization standards; commercial-card and B2B flows are next | D22: Participate; align C-09 with network protocols | E22: Copy (standards)
A23: Google AP2 / UCP | B23: Agents-to-Payments Protocol (Sep 2025, 60+ partners); v0.2 'human not present' (May 2026); crypto extension x402. | C23: Protocol layer for agent mandates | D23: Track; pilot with 5 clients | E23: Adapt
A24: Swift | B24: AI anomaly-detection fraud service live (Jan 2025); federated-learning experiment with Google Cloud and 13 banks doubled detection effectiveness (Sep 2025); blockchain ledger pilot with 17 banks incl. Citi (Jul 2026). | C24: Shared-signal fraud detection without sharing data; Citi already in the ledger pilot | D24: Join federated fraud phase 2 (E-08, C-06) | E24: Copy
A26: C. Enterprise AI adoption benchmarks — the 'middle of the pack' reality
A27: Source | B27: Finding | C27: So what for Services
A28: McKinsey State of AI 2026 (Aug 2026, n=1,719) | B28: ~90% use AI; 44% scaling enterprise-wide (54% at $1B+); ~20% scaling agents (40% at large firms); 37% report EBIT contribution; 6% 'high performers' redesign workflows 73% vs 25% and spend 15%+ of ICT budget on AI at 2x the rate; only 14% saw AI-driven headcount reduction; 20% constrained by token/operating costs. | C28: Workflow redesign — not tool access — separates high performers; plan for run-cost early (B2 loop)
A29: BCG Widening AI Value Gap (Sep 2025, n=1,250) | B29: 5% 'future-built', 35% scalers, 60% laggards; leaders 1.7x revenue growth, 3.6x TSR; agentic AI 17% of AI value now → 29% by 2028; payments/fintech among most mature sectors. | C29: Services' sector peers are ahead — the gap is closable but the clock is running
A30: MIT NANDA 'GenAI Divide' (Aug 2025) | B30: 95% of enterprise GenAI pilots show no measurable P&L impact; ~5% of custom tools reach production; vendor partnerships ~2x success of internal builds (methodology criticized). | C30: Pilot theater is the default failure mode (Systems View, archetype 1)
A31: Gartner (Jun 2025) | B31: >40% of agentic AI projects cancelled by end-2027 (cost, unclear value, weak risk controls); 'agent washing' widespread. | C31: Keep agentic bets small and bounded until controls and value are proven
A32: Deloitte State of AI in the Enterprise 2026 (Jan 2026, n=3,235) | B32: Workforce AI access ~60%; only 25% moved 40%+ of pilots to production; 21% have mature agent governance; ~75% plan agentic deployment within 2 years. | C32: Agent governance maturity is the scarce capability — build it (Operating Model, Tier 3–4)
A33: Evident AI Index (Oct 2025, 50 banks) | B33: 1 JPM, 2 Capital One, 3 RBC, 4 CommBank, 5 Morgan Stanley, 6 Wells, 7 UBS, 8 HSBC, 9 Goldman, 10 BofA; Citi #12 (from #8) with Talent 5th, Innovation 6th, Leadership 26th, Transparency 30th [verify sub-pillars]; 8 banks disclose portfolio ROI. | C33: Citi's gap is leadership narrative and transparency, not talent or innovation — precisely what a business-line value ledger and disclosure fix

Sheet Panel Review
A1: Panel Review — product leaders, strategists & business engineers, systems thinkers
A2: Each panelist's published framework is applied to this strategy. These are lens-applications, not quotations. The panel's synthesis is at the top; the individual reviews follow.
A4: Panel synthesis (what the panel wrote)
A5: Item | B5: Synthesis
A6: Convergent view 1 | B6: The diagnosis is right and unusual: the constraint is the governed path to production, not models or money. Most AI strategies for banks skip the diagnosis and start with use-case lists; this one earns its list.
A7: Convergent view 2 | B7: The commercial insight — that Services monetizes AI through balances and share of wallet, not feature fees — is the most defensible and most differentiating claim in the workbook. Lead with it in the conversation.
A8: Convergent view 3 | B8: Ontology-as-product is the right foundation and is unusually fundable here because it is the same work as the consent-order lineage remediation.
A9: Convergent view 4 | B9: Client co-creation is the demand engine; without named design partners the client mandate stays theoretical. The cohort must be in the first 90 days.
A10: Disagreement 1 | B10: Product leaders want fewer bets (5–6) with total focus; strategists accept 8–10 given five mandates; systems thinkers say bet count matters less than pipeline throughput. Resolution: 8 named bets, but only 3 'protected' at any time.
A11: Disagreement 2 | B11: How aggressive to be on agentic payments (C-09): business engineers see a platform-shift window; systems thinkers see a Tier-4 control problem and IMF's probabilistic-vs-deterministic tension. Resolution: small, convex position — 5 clients, explicit mandates, standards participation.
A12: Verdict | B12: Send it. It shows how AI strategy is done at a bank of this kind (pipeline, tiers, hub-and-spoke, regulatory map), takes a position (balances over fees; ontology before models), and gives the hiring manager something he can act on Monday (Now wave, cohort, ledger).
A14: A. Product leaders
A15: Panelist | B15: Lens | C15: Endorses | D15: Pushes back | E15: Change requested | F15: Landed in
A16: Marty Cagan | B16: Empowered teams; outcomes over output; product strategy = focus + insights + action | C16: business-line ownership with P&L, outcome KPIs per mandate, principles that resolve trade-offs. | D16: 40 use cases is a feature list; empowered teams need 3–5 problems to solve, not 40 solutions to build. Where are the product teams and their objectives? | E16: Frame the Now wave as 4 team objectives (servicing effort, onboarding time, RFP cycle, leakage) and let teams pick solutions. | F16: Strategy on a Page; Portfolio
A17: Teresa Torres | B17: Continuous discovery; opportunity solution trees; weekly customer touchpoints | C17: 10-client cohorts with monthly cadence; discovery synthesis from 3M+ inquiries (D-01). | D17: monthly is too slow for discovery; and inquiries tell you about today's product, not tomorrow's opportunity. | E17: Weekly touchpoints for the product trio on client products; opportunity tree per business line before scoring solutions. | F17: Pricing & Commercial (playbook); Roadmap WS6
A18: Shreyas Doshi | B18: LNO (leverage/neutral/overhead); clarity of the one thing; pre-mortems | C18: leverage points ranking; binding-constraint framing; 'measure P&L not pilots'. | D18: what is the one thing the hiring manager should remember? Too many good ideas dilute the memorable one. | E18: Open the conversation with one sentence: 'Services' AI gap is a pipeline gap, and the pipeline is the product I'd build.' Run a pre-mortem on the Now wave. | F18: Next Moves
A19: Gibson Biddle | B19: DHM: delight customers in hard-to-copy, margin-enhancing ways | C19: client products chosen where Citi's bank-side data (balances, flows) is hard for TMS vendors to copy. | D19: several client use cases are copyable by Kyriba/HighRadius on the ERP side; only balance-linked and execution-linked features are hard to copy. | E19: Score 'hard to copy' explicitly; favor C-02, C-03, C-09 over C-04 on that axis. | F19: Portfolio (strategic fit)
A20: Melissa Perri | B20: Escaping the build trap; outcome-based roadmaps | C20: exit criteria per period; value ledger; kill dates for pilots. | D20: roadmap cells still read like outputs in places (components with owners, markets live). | E20: Add an outcome column to the Roadmap in the workshop version. | F20: Roadmap
A21: April Dunford | B21: Positioning: competitive alternatives, unique attributes, value, best-fit customers | C21: segment table with willingness to pay and readiness; Commercial segment as pricing test bed. | D21: the client products lack a positioning statement against TMS vendors and fintechs. | E21: Write one line per client product: 'Unlike a TMS forecast, Citi's forecast sees your actual balances and executes.' | F21: Industry & Clients; Pricing
A23: B. Strategists, consultants and business engineers
A24: Panelist | B24: Lens | C24: Endorses | D24: Pushes back | E24: Change requested | F24: Landed in
A25: Richard Rumelt | B25: Strategy kernel: diagnosis, guiding policy, coherent action; avoid 'bad strategy' (goals dressed as strategy) | C25: the kernel is explicit on Strategy on a Page; the diagnosis names a constraint rather than an aspiration. | D25: 'AI-native' language in the maturity model drifts toward fluff; the coherent actions must be visibly mutually reinforcing. | E25: Keep the maturity labels but tie each action to the constraint it relieves (done in Systems View D). | F25: Strategy on a Page
A26: Roger Martin | B26: Strategy is choice: where to play, how to win; a plan is not a strategy | C26: choosing balances-over-fees, Commercial segment first, and pre-approved patterns are real choices with costs. | D26: where NOT to play is under-stated (consumer-style agentic checkout, building foundation models, competing with TMS vendors on ERP workflow). | E26: Add a 'not doing' list to the conversation (three items above). | F26: Next Moves
A27: Hamilton Helmer | B27: 7 Powers: scale economies, network effects, counter-positioning, switching costs, branding, cornered resource, process power | C27: process power (the governed pipeline) and cornered resource (bank-side balance/flow data) are the powers AI can create for Services. | D27: switching costs from AI features are weak unless features are embedded in execution (routing, sweeps), not just insight. | E27: Prioritize execution-embedded features (C-02, C-03) over insight-only features for durable power. | F27: Portfolio; Pricing
A28: Clayton Christensen | B28: Jobs to be done; low-end disruption | C28: JTBD by segment; recognition that Commercial/mid-market is the disruption entry point for fintechs. | D28: the strategy defends the high end well but the low-end response (self-serve, automated, cheaper) is thin. | E28: Make CitiDirect Commercial with embedded AI a first-class product bet, not a channel feature. | F28: Industry & Clients
A29: Michael Porter | B29: Operational effectiveness vs strategic positioning; activity-system fit | C29: separating efficiency (necessary, not sufficient) from client products (positioning). | D29: much of the Now wave is operational effectiveness every peer is also doing — it buys parity, not advantage. | E29: Be explicit: Now wave = parity and cash; Next wave = advantage. Do not oversell parity as strategy. | F29: Strategy on a Page (horizons)
A30: Gennaro Cuofano (The Business Engineer) | B30: BIA: constraint mapping (bottleneck/substitution/veto tests), AI Implementation Pyramid (≈70/15/10/5), FRED readiness test, Dual-Engine, Agentic four-phase moat building | C30: the binding-constraint discipline; the pyramid-shaped allocation (Portfolio Summary mix); agentic bets kept at the 'Foundation' phase until reliability and trust exist. | D30: the veto test is under-applied — regional COOs and MRM hold veto power; the strategy names them but does not yet give them a stake. | E30: Give MRM and regional COOs co-ownership of pipeline KPIs (cycle time) so veto holders become throughput owners. Run the FRED test with the hiring manager: Foundation (data), Resources, Executive alignment, Deployment capability. | F30: Systems View D; Operating Model B
A31: McKinsey / BCG practice view | B31: Domain-led transformation; rewire workflows; value gap; 'future-built' traits | C31: domain (business-line) ownership; workflow redesign in the talent workstream; value tracking. | D31: high performers spend 15%+ of ICT budget on AI at twice the rate of others — the $150M investment assumption may be low relative to a >$2B platform budget. | E31: Size investment as a share of platform spend (e.g., 10–15%) rather than a round number. | F31: Business Case
A33: C. Systems thinkers
A34: Panelist | B34: Lens | C34: Endorses | D34: Pushes back | E34: Change requested | F34: Landed in
A35: Donella Meadows | B35: Leverage points; stocks and flows; system purpose | C35: leverage points ranked; paradigm and goals above rules and parameters; stocks named. | D35: the slowest stock (trusted data) sets the pace of everything; the roadmap still front-loads use cases before the stock has accumulated. | E35: Gate Next-wave client products on ontology readiness ≥ 4, explicitly, in the roadmap. | F35: Systems View A/C; Roadmap WS2
A36: Peter Senge | B36: Learning organization; system archetypes; mental models | C36: archetypes to avoid; incident learning loop. | D36: 'shifting the burden' to vendors is the live risk given the Google Cloud dependency and vendor-led agent platforms. | E36: Name the internal capabilities that must never be outsourced (ontology, evals, domain workflows). | F36: Operating Model F
A37: Eliyahu Goldratt | B37: Theory of Constraints; five focusing steps; throughput accounting | C37: the five steps applied to the pipeline; subordinating intake to constraint capacity. | D37: measure throughput (use cases reaching verified value per quarter), not utilization of teams; local efficiencies elsewhere are noise. | E37: One throughput KPI at the top of the value report. | F37: Systems View D
A38: Russell Ackoff | B38: Systems purpose; idealized design; doing the right thing vs doing the wrong thing righter | C38: the purpose statement; designing the pipeline from the ideal end-state backwards. | D38: efficiency use cases risk 'doing the wrong thing righter' — automating exceptions instead of eliminating their causes (ISO 20022 data quality, client formatting). | E38: Pair every exception-automation use case with a root-cause elimination metric (exceptions per million). | F38: Portfolio KPIs
A39: Jay Forrester | B39: System dynamics; delays; policy resistance | C39: delays table; balancing loops named. | D39: policy resistance is likely — business lines will route around the single pipeline if it is slow. The fast lane must be visibly fast within 90 days. | E39: Publish cycle-time SLAs early and hit them for Tier 1–2. | F39: Systems View F; Roadmap WS3
A40: Stafford Beer | B40: Viable System Model: operations (S1), coordination (S2), control (S3), intelligence (S4), policy (S5) | C40: hub-and-spoke maps to VSM — spokes are S1, pipeline/standards are S2–S3, this role's market and client sensing is S4, Head of Services is S5. | D40: S4 (intelligence about the environment — regulators, networks, fintechs) is thin in most bank AI orgs; the regulatory map and benchmarks must be maintained, not one-off. | E40: Standing S4 function: quarterly environment scan feeding the portfolio re-score. | F40: Operating Model B; Benchmarks
A41: W. Edwards Deming | B41: Variation; measurement; drive out fear | C41: eval harness and monitoring as continuous measurement. | D41: in a consent-order environment fear suppresses reporting of AI incidents; without psychological safety the learning loop fails. | E41: Blameless incident reviews for AI, reported upward as learning, not failure. | F41: Systems View B3
A42: Nassim Taleb | B42: Antifragility; barbell; via negativa | C42: barbell — mostly proven productivity/efficiency plus small convex bets (agentic rails, data products). | D42: any single client-facing failure is asymmetric downside in a bank; and 'via negativa' — what to stop doing — is missing. | E42: List what to stop: unowned pilots, bespoke builds, activity metrics as success measures. | F42: Portfolio Summary mix; Next Moves
A43: John Boyd | B43: OODA loop; tempo as advantage | C43: cycle time as a first-class KPI. | D43: peers already publish faster tempo (BofA 45 POCs → 15 live; JPM doubling production use cases yearly); the plan's 90/180-day SLAs must beat theirs to matter. | E43: Benchmark tempo, not just value, against peers quarterly. | F43: Roadmap WS3; Benchmarks
A45: Attribution: Business Engineering frameworks (constraint mapping, AI Implementation Pyramid, FRED test, Dual-Engine, agentic moat phases) — Analysis by The Business Engineer, by Gennaro Cuofano (businessengineer.ai). Other lenses are the named authors' published frameworks applied by the author of this workbook.

Sheet Next Moves (AS)
A1: Next Moves — how to use this with the hiring manager (for you, not for him)
A2: Briefcase Technique: bring the diagnosis and a plan, not a list. Peer-level tone; you are evaluating whether the mandate is real. Everything below is optional except the verify list.
A4: A. Packaging (what to send, in what order)
A5: Step | B5: What | C5: Why | D5: Note
A6: 1. One-page memo (send first) | B6: Diagnosis (pipeline gap, not capability gap) → guiding policy (ontology before models; balances over fees; one pipeline) → 3 protected bets for the business line he owns → one ask (decision rights + Finance-owned ledger). No more than 400 words. | C6: Rumelt kernel; Doshi's one thing | D6: Draft available on request
A7: 2. This workbook (attach) | B7: Position it as 'how I'd run the first 90 days' plus 'how the domain does this' — not as a finished strategy. Point him to Strategy on a Page, Portfolio, Operating Model. | C7: Briefcase Technique
A8: 3. Offer a working session | B8: Propose a 60-minute scoring workshop with his team using the Portfolio tab — it converts you from candidate to collaborator and surfaces his real priorities. | C8: Sethi; Torres
A9: 4. Follow-up artifact | B9: After the conversation: a one-page 30-60-90 for the specific business line (Payments or LMS) and one deep-dive (cash-flow forecasting product one-pager, or fee-leakage engine design). | C9: Cagan | D9: Choose based on which line he owns
A11: B. Calibrated questions to ask him (each reveals whether the mandate is real)
A12: Theme | B12: Question | C12: What the answer tells you
A13: Scope | B13: Which business line is this role scoped to — Payments or Liquidity Management — and who is the executive sponsor for its AI P&L? | C13: Tells you whether there is a P&L owner behind the JD's language
A14: Pipeline | B14: What is the current median time from a GenAI use-case charter to production in Services, and where does it wait? | C14: Tests the diagnosis; if he doesn't know, that is the answer
A15: Value | B15: Of the 50+ use cases in the pipeline, how many have Finance-attributed value today? | C15: Tests the measurement gap
A16: Data | B16: Who owns the entity model for Services — Platforms & Data Solutions? — and is lineage remediation funded as a product or as a compliance project? | C16: Tests ontology readiness and funding vehicle
A17: Structure | B17: What changed for business-line AI leads when the firmwide AI organization was reorganized in May 2026? | C17: Tests hub/spoke decision rights
A18: Clients | B18: Which clients are already co-creating on AI, and under what agreement? | C18: Tests whether the client mandate exists or is aspirational
A19: Money | B19: How much of the Investor Day investment envelope reaches Services AI, and is it in the >$2B platform budget or incremental? | C19: Tests resource reality (FRED test)
A21: C. Objections you will hear, and the honest response
A22: Objection | B22: Response | C22: Basis
A23: 'Your background is Wealth and Cards, not transaction banking.' | B23: Acknowledge directly, then bridge: regulated AI delivery at Citi (Applied AI & Partnerships; AI & Architecture), client co-creation and partnership at scale ($1B partnership), and the fact that the constraint here is a pipeline and ontology problem — which is domain-agnostic — while the domain deconstruction in this workbook shows you have done the homework. Name the two areas you would learn fastest (payments operations detail; liquidity structures by market). | C23: Materials playbook: acknowledge gaps directly, pair with transferable strengths
A24: 'This is a lot of tabs — what would you actually do first?' | B24: The Now wave plus the pipeline: E-01 in all markets, E-10, I-01, I-03, P-01; ontology v0; control library v1; cohort recruitment. One sentence each. | C24: Doshi's one thing
A25: 'We already have 50 use cases.' | B25: Agree — the problem is not ideas. Ask which five have verified value and what the cycle time is. Offer the scoring workshop. | C25: Diagnosis
A26: 'Is the $ business case credible?' | B26: It is a structure with public inputs; the only claim you defend is the shape (balances and cost-to-serve dominate; feature fees are small). Offer to replace inputs with his baselines in a week. | C26: Business Case
A27: Seniority signal (the BNY feedback) | B27: Speak in decision rights, P&L and trade-offs — what you would protect, stop and fund — not in features. Position as evaluating the mandate: 'If the ledger and decision rights aren't there, the role can't deliver what the JD promises.' | C27: Overview notes; positioning rule
A29: D. What NOT to do (via negativa — say these out loud, they signal judgment)
A30: Not doing | B30: Because
A31: Build foundation models or compete with the enterprise platform | B31: Compose on Gemini/Anthropic/Llama via the hub; the moat is ontology, evals and domain workflows
A32: Chase consumer-style agentic checkout | B32: Stripe called it overhyped; OpenAI Instant Checkout was discontinued; B2B agent mandates are the relevant frontier
A33: Compete with TMS/AR vendors on ERP workflow | B33: Partner there; compete on bank-side balances, flows and execution
A34: Count prompts and users as success | B34: They are leading indicators; the ledger is the scoreboard
A35: Run unowned pilots | B35: Every pilot has a production owner, value hypothesis and kill date
A37: E. More you can do (extensions of this workbook)
A38: Extension | B38: What | C38: Why
A39: Run the scoring workshop | B39: Portfolio tab with his team; replace the ratings; produce the Now wave with owners. 60 minutes. | C39: Highest leverage — turns the artifact into a shared plan
A40: Client-interview mini-study | B40: 5–8 conversations with treasurers/FI operations contacts in your network on forecasting, routing and agentic treasury; add as a 'Voice of client' tab. | C40: Evidence for the client mandate; Torres cadence
A41: Replace business-case inputs | B41: Ask for servicing headcount, onboarding volumes, fee revenue by product, ops cost base; rerun sensitivities. | C41: Credibility
A42: One use-case charter | B42: Write the intake charter for C-01 or P-01 exactly as the pipeline (Operating Model A) requires: entities, tier, controls, value hypothesis, owner. | C42: Demonstrates the pipeline in miniature
A43: Positioning statements | B43: One line per client product vs TMS vendors and fintechs (Dunford). | C43: Client mandate
A44: Evident sub-pillar map | B44: Map how the role moves Leadership and Transparency pillars (disclosure, public case studies, conference presence). | C44: Speaks to the enterprise narrative
A45: Regulatory calendar | B45: One-page calendar: EU AI Act Dec 2027, Colorado Jan 2027, MAS final guidelines, HKMA Sep 2026, SR 26-2 RFI. | C45: S4 intelligence (Beer)
A47: F. Verify before use (facts that conflicted or could not be confirmed)
A48: Item | B48: Status
A49: Services FY2025 revenue basis | B49: $21.3B / RoTCE 28.6% (press release) vs $22.6B / 24.6% (Investor Day, likely managed basis). Workbook uses $21.3B.
A50: Agent Assist scale | B50: 1,200 agents live (American Banker, Apr 2026) vs 6,000 agents / 72 countries (Investor Day target). Workbook labels 6,000 as target.
A51: Business-line leadership | B51: Confirmed: Shahmir Khaliq (Services), Debopama Sen (Payments), Chris Cox (Investor Services, from Mar 2025). Not confirmed for 2026: head of Trade & Working Capital, head of Issuer Services, Stephen Randall (LMS). Do not name them in the memo unless he confirms.
A52: Firmwide AI organization | B52: David Griffiths became Group Head of AI (May 2026); a job posting describes merged Head-of-AI/CTO responsibilities — confirm current structure with him.
A53: Evident sub-pillar ranks | B53: Citi #12 headline corroborated; sub-pillar ranks (Talent 5th, Leadership 26th, Transparency 30th) from a single fetch.
A54: MAS final AI risk guidelines | B54: Consultation closed Jan 2026; final issuance not confirmed as of 22 Sep 2026.
A55: Fee leakage rate | B55: 1–3% is an industry rule of thumb, not a Citi figure.

Sheet Sources
A1: Sources
A2: Primary sources preferred; secondary sources marked. Retrieved 22 Sep 2026.
A4: Source | B4: URL
A5: Citi Q2 2026 results (press release / 8-K) | B5: https://www.sec.gov/Archives/edgar/data/831001/000110465926083383/c-20260714xex99d1.htm
A6: Citi FY2025 / Q4 2025 results | B6: https://www.citigroup.com/rcs/citigpa/storage/public/Earnings/Q42025/2025prqtr4rslt.pdf
A7: Citi Investor Day 2026 — Services presentation and transcript | B7: https://www.citigroup.com/rcs/citigpa/storage/public/investor-day/citi-ID26-services-presentation.pdf ; https://www.citigroup.com/rcs/citigpa/storage/public/investor-day/citi-ID26-services-presentation-transcript.pdf
A8: Citi 2025 Annual Report | B8: https://www.citigroup.com/rcs/citigpa/storage/public/Annual_Report/2025/citi-2025-annual-report.pdf
A9: Citi Q2 2026 earnings call transcript | B9: https://www.fool.com/earnings/call-transcripts/2026/07/21/citi-c-q2-2026-earnings-call-transcript/
A10: Khaliq at UBS Financial Services conference (Feb 2026) | B10: https://www.investing.com/news/transcripts/citigroup-at-ubs-financial-services-strategic-growth-and-innovation-93CH-4498521
A11: American Banker — four ways AI is making Citi's Services unit more efficient (Apr 2026) | B11: https://www.americanbanker.com/news/four-ways-ai-is-making-citis-services-unit-more-efficient
A12: Payments Dive — Citi Payments / Debopama Sen (Mar 2026) | B12: https://www.paymentsdive.com/news/citi-payments-advances-debopama-sen-real-time-stablecoin-fednow-agentic-ai/815818/
A13: Citi Stylus Workspaces agentic pilot (Sep 2025) | B13: https://www.citigroup.com/global/news/press-release/2025/citi-unveils-citi-stylus-workspaces-agentic-ai-turbocharging-productivity
A14: American Banker — Citi agentic AI to 40,000 developers (Jul 2025) | B14: https://www.americanbanker.com/news/citi-is-rolling-out-agentic-ai-to-its-40-000-developers
A15: Banking Dive — Citi (Tim Ryan) at Money20/20 (Oct 2025) | B15: https://www.bankingdive.com/news/citi-ryan-ai-banking-technology-innovation-money2020/804138/
... A53: Job posting — AI Product Strategy, Global Services – Director (Citi via Built In) | B53: https://builtin.com/job/ai-product-strategy-global-services-director/10653570
